{
  "videos": {
    "L2N85Bfw2Rg": {
      "videoId": "L2N85Bfw2Rg",
      "title": "새누리당 의원들, 북한 축구팀 응원",
      "description": "새누리당 의원들이 인천 아시안 게임 축구 결승전, 북한과 일본 경기장을 찾았습니다. 누구를 응원했을까요?\n\n[Ch.19] 세상에 없는 TV 이제 시작합니다. \n★홈페이지 : www.tvchosun.com \n기사 더 보기 ▶ http://news.tvchosun.com/site/data/html_dir/2014/10/01/2014100190332.html",
      "publishedAt": "2014-10-01T14:13:30Z",
      "duration": "PT1M11S",
      "viewCount": 4359,
      "likeCount": 11,
      "commentCount": 8,
      "tags": [
        "TV조선",
        "티비조선",
        "조선일보",
        "종편",
        "종합편성",
        "티브이조선",
        "방송사",
        "TV조선뉴스",
        "뉴스",
        "뉴스프로그램"
      ],
      "liveBroadcastContent": "none",
      "liveStreamingDetails": null,
      "actualPubAt": "2014-10-01T14:13:30Z",
      "channelId": "UCWlV3Lz_55UaX4JsMj-z__Q",
      "channelName": "뉴스TVCHOSUN",
      "collectedAt": "2025-08-21T10:46:16Z"
    },
    "nl4BDY-ZTBk": {
      "videoId": "nl4BDY-ZTBk",
      "title": "[TV조선 단독] 김무성, 방중 기간 시진핑 만난다",
      "description": "이달 중순에 중국을 방문하는 새누리당 김무성 대표가 시진핑 주석 등 중국 핵심 지도부를 만날 가능성이 크다고 합니다. 김무성 대표는 이번 방중에 상당한 의미를 두고 있는것 같습니다.\n\n[Ch.19] 세상에 없는 TV 이제 시작합니다. \n★홈페이지 : www.tvchosun.com \n기사 더 보기 ▶ http://news.tvchosun.com/site/data/html_dir/2014/10/01/2014100190334.html",
      "publishedAt": "2014-10-01T14:20:29Z",
      "duration": "PT1M45S",
      "viewCount": 349,
      "likeCount": 0,
      "commentCount": 0,
      "tags": [
        "TV조선",
        "티비조선",
        "조선일보",
        "종편",
        "종합편성",
        "티브이조선",
        "방송사",
        "TV조선뉴스",
        "뉴스",
        "뉴스프로그램"
      ],
      "liveBroadcastContent": "none",
      "liveStreamingDetails": null,
      "actualPubAt": "2014-10-01T14:20:29Z",
      "channelId": "UCWlV3Lz_55UaX4JsMj-z__Q",
      "channelName": "뉴스TVCHOSUN",
      "collectedAt": "2025-08-21T10:46:16Z"
    },
    "YYZdrO-DzX8": {
      "videoId": "YYZdrO-DzX8",
      "title": "이완구-박영선 3차례 파고 넘어 의회정치 복원",
      "description": "새누리당 이완구 원내대표와 새정치민주연합 박영선 원내대표는 유족들의 반발에도 불구하고 두번이 재협상 끝에 세월호 특별법을 타결지었습니다. 이번 합의에는 여야 리덩인 김무성 대표와 문희상 비상대책위원장도 조연으로서 역할을 했습니다.\n\n[Ch.19] 세상에 없는 TV 이제 시작합니다. \n★홈페이지 : www.tvchosun.com \n기사 더 보기 ▶ http://news.tvchosun.com/site/data/html_dir/2014/10/01/2014100190131.html",
      "publishedAt": "2014-10-01T04:21:22Z",
      "duration": "PT1M27S",
      "viewCount": 156,
      "likeCount": 3,
      "commentCount": 0,
      "tags": [
        "TV조선",
        "티비조선",
        "조선일보",
        "종편",
        "종합편성",
        "티브이조선",
        "방송사",
        "TV조선뉴스",
        "뉴스",
        "뉴스프로그램"
      ],
      "liveBroadcastContent": "none",
      "liveStreamingDetails": null,
      "actualPubAt": "2014-10-01T04:21:22Z",
      "channelId": "UCWlV3Lz_55UaX4JsMj-z__Q",
      "channelName": "뉴스TVCHOSUN",
      "collectedAt": "2025-08-21T10:46:16Z"
    },
    "Dk3ip_D8Nkk": {
      "videoId": "Dk3ip_D8Nkk",
      "title": "제시카·니콜·크리스…잇단 아이돌 멤버 탈퇴, 왜?",
      "description": "한국을 대표하는 걸그룹 '소녀 시대'의 멤버 제시카가 그룹 활동을 중단했습니다. '일방적 퇴출'이냐 '탈퇴'냐를 두고 제시카와 소속사 측의 공방이 거셉니다. \n\n[Ch.19] 세상에 없는 TV 이제 시작합니다. \n★홈페이지 : www.tvchosun.com \n기사 더 보기 ▶ http://news.tvchosun.com/site/data/html_dir/2014/10/01/2014100190306.html",
      "publishedAt": "2014-10-01T14:00:23Z",
      "duration": "PT1M32S",
      "viewCount": 2435,
      "likeCount": 5,
      "commentCount": 0,
      "tags": [
        "TV조선",
        "티비조선",
        "조선일보",
        "종편",
        "종합편성",
        "티브이조선",
        "방송사",
        "TV조선뉴스",
        "뉴스",
        "뉴스프로그램"
      ],
      "liveBroadcastContent": "none",
      "liveStreamingDetails": null,
      "actualPubAt": "2014-10-01T14:00:23Z",
      "channelId": "UCWlV3Lz_55UaX4JsMj-z__Q",
      "channelName": "뉴스TVCHOSUN",
      "collectedAt": "2025-08-21T10:46:16Z"
    },
    "rowbh6Kpuxg": {
      "videoId": "rowbh6Kpuxg",
      "title": "소녀시대, 제시카 빠진다…잇단 아이돌 멤버 탈퇴 논란",
      "description": "걸그룹 '소녀시대'의 멤버 제시카가 그룹활동을 중단하면서 이제, 8인체제로 운영됩니다. '퇴출'이냐 '탈퇴'냐를 두고 제시카와 소속사의 입장은 엇갈리고 있는데요, 잇단 아이돌 멤버의 탈퇴 논란이 다시 수면 위로 떠오르고 있습니다.\n\n[Ch.19] 세상에 없는 TV 이제 시작합니다. \n★홈페이지 : www.tvchosun.com \n기사 더 보기 ▶ http://news.tvchosun.com/site/data/html_dir/2014/10/01/2014100190163.html",
      "publishedAt": "2014-10-01T04:22:21Z",
      "duration": "PT1M31S",
      "viewCount": 2458,
      "likeCount": 8,
      "commentCount": 1,
      "tags": [
        "TV조선",
        "티비조선",
        "조선일보",
        "종편",
        "종합편성",
        "티브이조선",
        "방송사",
        "TV조선뉴스",
        "뉴스",
        "뉴스프로그램"
      ],
      "liveBroadcastContent": "none",
      "liveStreamingDetails": null,
      "actualPubAt": "2014-10-01T04:22:21Z",
      "channelId": "UCWlV3Lz_55UaX4JsMj-z__Q",
      "channelName": "뉴스TVCHOSUN",
      "collectedAt": "2025-08-21T10:46:16Z"
    },
    "uAnqMMw9sZ0": {
      "videoId": "uAnqMMw9sZ0",
      "title": "이건희 입원 144일, 아들 이재용은 지금…",
      "description": "이재용 삼성전자 부회장이 병상에 있는 아버지를 대신해 광폭 행보에 나서고 있습니다. 계속되는 실적 악화에 리더십을 강화하고 대내외적으로 자신의 존재감을 각인시키려는 것 같습니다. 이건희 회장은 더디지만 상태가 계속 좋아지고는 있다고 합니다. \n\n[Ch.19] 세상에 없는 TV 이제 시작합니다. \n★홈페이지 : www.tvchosun.com \n기사 더 보기 ▶ http://news.tvchosun.com/site/data/html_dir/2014/10/01/2014100190300.html",
      "publishedAt": "2014-10-01T14:01:28Z",
      "duration": "PT2M1S",
      "viewCount": 1071,
      "likeCount": 2,
      "commentCount": 0,
      "tags": [
        "TV조선",
        "티비조선",
        "조선일보",
        "종편",
        "종합편성",
        "티브이조선",
        "방송사",
        "TV조선뉴스",
        "뉴스",
        "뉴스프로그램"
      ],
      "liveBroadcastContent": "none",
      "liveStreamingDetails": null,
      "actualPubAt": "2014-10-01T14:01:28Z",
      "channelId": "UCWlV3Lz_55UaX4JsMj-z__Q",
      "channelName": "뉴스TVCHOSUN",
      "collectedAt": "2025-08-21T10:46:16Z"
    },
    "WDETgCGKQ0g": {
      "videoId": "WDETgCGKQ0g",
      "title": "[변상욱의 기자수첩]“도대체 지구촌 어느 대학이 좋은 대학일까?” (20141001)",
      "description": "[변상욱의 기자수첩]“도대체 지구촌 어느 대학이 좋은 대학일까?”\n\n대담 : 변상욱 대기자",
      "publishedAt": "2014-10-01T01:50:15Z",
      "duration": "PT7M53S",
      "viewCount": 259,
      "likeCount": 3,
      "commentCount": 0,
      "tags": [
        "김현정",
        "뉴스쇼",
        "CBS",
        "변상욱",
        "지구촌 어느 대학이 좋을까"
      ],
      "liveBroadcastContent": "none",
      "liveStreamingDetails": null,
      "actualPubAt": "2014-10-01T01:50:15Z",
      "channelId": "UC4Aa3OPkMenwTANpf0oWVRQ",
      "channelName": "CBS 김현정의 뉴스쇼",
      "collectedAt": "2025-08-22T14:03:28Z"
    },
    "AHwXjQuwUlU": {
      "videoId": "AHwXjQuwUlU",
      "title": "[김현정의 뉴스쇼] \"‘우산 혁명’ 중인 홍콩, 제 2의 천안문 사태 걱정돼\"(20141001)",
      "description": "\"‘우산 혁명’ 중인 홍콩, 제 2의 천안문 사태 걱정돼\"\n\n■ 방송 : CBS 라디오 FM 98.1 (07:30~09:00)\n■ 진행 : 김현정 앵커\n■ 대담 : 전기범 (홍콩 거주자) \n\n홍콩의 상황이 심상치가 않습니다. 지난 주말부터 홍콩 시민들이 민주화시위를 시작했는데요. 중국 경찰은 지금 최루탄 발포하고 있고, 총을 쏴도 된다는 이런 얘기가 나왔다는 소문도 들립니다. 더군다나 오늘은 중국 최대의 명절이죠, 국경절입니다. 오늘부터 내일 이틀 동안 시민들이 대거 거리로 몰려나올 거라는 관측이 나오는데요. 중국 정부는 ‘홍콩 시민들 요구는 절대 받아들일 수가 없는 거다’라고 강경하게 맞서고 있기 때문에 정말로 시위대에 총 쏘는 것 아닌가. 제2의 천안문 사태 벌어지는 것 아니냐. 이런 세계의 우려들 나오고 있습니다. 홍콩 역사상 최대 규모의 시위. 도대체 홍콩시민들은 무엇 때문에 이렇게 분노하고 있는 건지 홍콩 현지를 직접 연결을 해 보죠. 11년째 거주 중인 한인이세요. 전기범 씨 연결돼 있습니다. 전 선생님, 안녕하세요?",
      "publishedAt": "2014-10-01T01:45:30Z",
      "duration": "PT9M25S",
      "viewCount": 1009,
      "likeCount": 4,
      "commentCount": 0,
      "tags": [
        "김현정",
        "뉴스쇼",
        "홍콩",
        "우산혁명",
        "제2의 천안문사태",
        "CBS"
      ],
      "liveBroadcastContent": "none",
      "liveStreamingDetails": null,
      "actualPubAt": "2014-10-01T01:45:30Z",
      "channelId": "UC4Aa3OPkMenwTANpf0oWVRQ",
      "channelName": "CBS 김현정의 뉴스쇼",
      "collectedAt": "2025-08-22T14:03:28Z"
    },
    "cO1kxegu6Og": {
      "videoId": "cO1kxegu6Og",
      "title": "[김현정의 뉴스쇼] \"유람선 사고로 줄줄이 예약취소..홍도는 웁니다\" (20141001)",
      "description": "\"유람선 사고로 줄줄이 예약취소..홍도는 웁니다\"\n\n■ 방송 : CBS 라디오 FM 98.1 (07:30~09:00)\n■ 진행 : 김현정 앵커\n■ 대담 : 김준호 (썬플라워호 선장), 김정남 (홍도 청년회장)\n\n어제 오전 9시, 그러니까 저희가 방송을 마치고 내려가자마자 급박한 소식이 터져 나왔습니다. 전남 홍도 해상에서 승객과 승무원 110명이 탄 바캉스호라는 유람선이 좌초된 건데요. 다행히 탑승객 전원이 구조는 됐습니다만, 몇 가지 면에서 세월호를 떠올리게 하는 아찔한 사고였습니다. 특히 이 유람선은 너무 오래돼서 처음 도입될 때부터 주민들 우려가 컸다고 하는데요. 이 사고를 자세히 들여다보죠. 먼저 어제 사고 현장에 출동해서 80여 명의 승객을 구조한 분이세요. 썬플라워호 김준호 선장부터 연결해 보겠습니다. 선장님, 나와 계십니까?",
      "publishedAt": "2014-10-01T01:45:22Z",
      "duration": "PT8M55S",
      "viewCount": 159,
      "likeCount": 1,
      "commentCount": 0,
      "tags": [
        "김현정",
        "뉴스쇼",
        "유람선 사고",
        "홍도",
        "CBS"
      ],
      "liveBroadcastContent": "none",
      "liveStreamingDetails": null,
      "actualPubAt": "2014-10-01T01:45:22Z",
      "channelId": "UC4Aa3OPkMenwTANpf0oWVRQ",
      "channelName": "CBS 김현정의 뉴스쇼",
      "collectedAt": "2025-08-22T14:03:28Z"
    },
    "-I5DZUJT6js": {
      "videoId": "-I5DZUJT6js",
      "title": "[김현정의 뉴스쇼] 윤병세 \"연내 한일정상회담? 아직은 먹구름\" (20141001)",
      "description": "윤병세 \"연내 한일정상회담? 아직은 먹구름\"\n\n■ 방송 : CBS 라디오 FM 98.1 (07:30~09:00)\n■ 진행 : 김현정 앵커\n■ 대담 : 윤병세 (외교부 장관) \n\n얼마 전 박근혜 대통령이 UN총회에서 기조연설을 했습니다. 북한과 일본에 대해서 어떤 발언을 할까, 특히 관심이 모아졌는데요. 그도 그럴 것이 지금 북한과도, 일본과도 관계가 좀 껄끄러운 상태기 때문에 대통령의 발언을 보면 앞으로의 남북관계, 한일관계가 관측 가능한 상황이었죠. 그런데 박 대통령은 북에 대해서는 핵포기와 인권문제 개선을 강하게 촉구한 반면에 일본군 위안부 문제에 대해서는 비판의 수위가 좀 낮았습니다. 우리 외교부가 구상하는 남북관계와 한일관계, 지금부터 이분과 함께 짚어보죠. 윤병세 외교부 장관 연결을 해 보죠. 장관님 안녕하세요.",
      "publishedAt": "2014-10-01T01:43:05Z",
      "duration": "PT12M11S",
      "viewCount": 129,
      "likeCount": 2,
      "commentCount": 0,
      "tags": [
        "김현정",
        "뉴스쇼",
        "윤병세",
        "연내 한일정상회담 먹구름",
        "CBS"
      ],
      "liveBroadcastContent": "none",
      "liveStreamingDetails": null,
      "actualPubAt": "2014-10-01T01:43:05Z",
      "channelId": "UC4Aa3OPkMenwTANpf0oWVRQ",
      "channelName": "CBS 김현정의 뉴스쇼",
      "collectedAt": "2025-08-22T14:03:28Z"
    },
    "LWXJSpEPR2s": {
      "videoId": "LWXJSpEPR2s",
      "title": "[김현정의 뉴스쇼] 세월호 유족 \"어떻게 버텨왔는데 이런 안을..\" (20141001)",
      "description": "세월호 유족 \"어떻게 버텨왔는데 이런 안을..\"\n\n■ 방송 : CBS 라디오 FM 98.1 (07:30~09:00)\n■ 진행 : 김현정 앵커\n■ 대담 : 김성실 세월호 가족대책위 부위원장 (故 동혁 군 어머니) \n\n세월호 참사 167일 만에 여야가 세월호 특별법을 최종 합의했습니다. 여기서 합의란 새정치연합의 의원총회까지 통과한 최종 타결안입니다. 이것을 타결하고 나서 국회 본회의도 열었죠. 그런데 유가족들이 이 안에 대해서 다시 반대하고 나서면서 상황이 복잡해졌습니다. 그제와 어제 여야와 유가족이 함께 논의를 한 것으로 우리는 알고 있었는데 왜 유족들은 반대하고 나선 걸까요? 이 혼란스러운 상황들 좀 정리해 보겠습니다. 세월호 가족대책위의 김성실 부위원장, 동혁이 어머니세요. 직접 연결을 해 보죠. 김성실 부위원장님 나와 계세요?",
      "publishedAt": "2014-10-01T01:39:58Z",
      "duration": "PT8M15S",
      "viewCount": 399,
      "likeCount": 2,
      "commentCount": 0,
      "tags": [
        "김현정",
        "뉴스쇼",
        "세월호 유족",
        "CBS"
      ],
      "liveBroadcastContent": "none",
      "liveStreamingDetails": null,
      "actualPubAt": "2014-10-01T01:39:58Z",
      "channelId": "UC4Aa3OPkMenwTANpf0oWVRQ",
      "channelName": "CBS 김현정의 뉴스쇼",
      "collectedAt": "2025-08-22T14:03:28Z"
    },
    "MVc2eHE37CY": {
      "videoId": "MVc2eHE37CY",
      "title": "[단독] 4대강 수질 악화…녹조 제거에 4000억 '헛돈'",
      "description": "방송사 : JTBC http://www.jtbc.co.kr\n▶ JTBC 뉴스9 월~금 21시00분 방송\n▶ 홈페이지 : http://news.jtbc.co.kr\n▶ 공식 트위터 : https://twitter.com/JTBC_news\n▶ 공식 페이스북 : https://www.facebook.com/jtbcnews\n\n4대강 사업 그 후, 오늘(1일)도 저희는 국민들이 낸 세금이 얼마나 헛되이 쓰였는지 그리고 또 앞으로 들어갈 돈은 얼마나 많은 것인지, 여기에 집중하겠습니다. '녹조라떼' 4대강 사업이 불러온 큰 논란거리 중 하나였고 유행어처럼 됐습니다. 정부는 녹조를 제거하기 위해, 녹조의 먹이가 되는 '인'을 낮추기 위한 총인처리시설 등 다양한 방법을 동원해서 만들어 놨습니다. 여기에만 4000억 원이 넘는 돈이 들어갔습니다. 정부는 수질이 개선되고 있다고 발표해 왔는데 최근 환경부 자료를 입수해 확인한 결과 4대강 수질은 크게 악화된 것으로 나타났습니다. \n\n안지현 기자의 단독 보도입니다.",
      "publishedAt": "2014-10-01T14:16:05Z",
      "duration": "PT2M51S",
      "viewCount": 6706,
      "likeCount": 27,
      "commentCount": 20,
      "tags": [
        "JTBC",
        "JTBC NEWS",
        "JTBC 뉴스",
        "손석희",
        "안지현",
        "4대강",
        "녹조현상",
        "녹조라떼",
        "JTBC 단독",
        "환경오염"
      ],
      "liveBroadcastContent": "none",
      "liveStreamingDetails": null,
      "actualPubAt": "2014-10-01T14:16:05Z",
      "channelId": "UCsU-I-vHLiaMfV_ceaYz5rQ",
      "channelName": "JTBC News",
      "collectedAt": "2025-08-25T21:08:23Z"
    },
    "I7FZP4c7ZKc": {
      "videoId": "I7FZP4c7ZKc",
      "title": "[팩트체크] AG '동네 운동회' 수준?…엽기 운영 논란",
      "description": "방송사 : JTBC http://www.jtbc.co.kr\n▶ JTBC 뉴스9 월~금 21시00분 방송\n▶ 홈페이지 : http://news.jtbc.co.kr\n▶ 공식 트위터 : https://twitter.com/JTBC_news\n▶ 공식 페이스북 : https://www.facebook.com/jtbcnews\n\n\n기다리시던 팩트체크 시간입니다. 오늘(1일)도 팩트체커, 김필규 기자 나와 있습니다.\n\n여러가지 이야기가 많이 나왔습니다. 저희도 몇 차례 보도해 드렸고, 오늘 이와 관련된 내용들을 다 검증을 해 봤습니까?",
      "publishedAt": "2014-10-01T14:19:07Z",
      "duration": "PT8M20S",
      "viewCount": 14367,
      "likeCount": 69,
      "commentCount": 11,
      "tags": [
        "JTBC",
        "JTBC NEWS",
        "JTBC 뉴스",
        "손석희",
        "김필규",
        "뉴스룸",
        "뉴스9",
        "팩트체크",
        "아시안게임",
        "인천아시안게임",
        "AG",
        "쑨웨이",
        "FIBA"
      ],
      "liveBroadcastContent": "none",
      "liveStreamingDetails": null,
      "actualPubAt": "2014-10-01T14:19:07Z",
      "channelId": "UCsU-I-vHLiaMfV_ceaYz5rQ",
      "channelName": "JTBC News",
      "collectedAt": "2025-08-25T21:08:23Z"
    },
    "KVFSGHzFtvA": {
      "videoId": "KVFSGHzFtvA",
      "title": "더 내고 덜 받는 공무원 연금 개혁안, 해답은?_채널A_쾌도난마 704회",
      "description": "공식홈페이지 : http://tv.ichannela.com/culture/sisatalk\n[하종대의 쾌도난마] 14/09/30 방송 704회\n\n[2014.09.30]\n김용하 前 한국연금학회 전 회장, 윤석명 한국보건사회연구원\n\n공무원연금 개혁, 찬성 70%… 이유는?\n공무원연금, 국민연금과 뭐가 다른가?\n\n향후 5년간 공무원 연금 적자 18조 4천억 원\n당·정·청 \"공무원연금 정부최종안 10월 중순 마련\"\n\n공무원연금 개혁할 시 적자 얼마나 줄어드나?\n말 많던 공무원연금 도마 위에 오르다\n\n공무원 노조 \"이해 당사자 배제한 연금개혁 규탄\"\n공무원 노조 \"조삼모사 연금개혁, 원숭이 취급 말라\"\n공무원 연금 개혁 '334조 절감'vs'젊은 공무원 고통'\n\n연금개혁 걱정에 공무원 명예퇴직 급증\n올해 8876명 공무원 명퇴 러시… \"연금 깎일라\"\n\n당·정·청 \"공무원연금 정부최종안 10월 중순 마련\"\n박 대통령, 오늘 국무회의 주제… '공무원 연금' 논의\n\n9급 공무원, 10년 일해도 5급 초봉 못 미쳐\n공무원 연금 개선안, 현직·하위직이 더 깎인다 ○ 기사 보기\n\n▶채널A뉴스 구독\nhttps://www.youtube.com/tvchanews?sub_confirmation=1\n\n[채널A 뉴스·시사 프로그램｜유튜브 라이브 방송시간]\n\n〈평일〉\n08시 00분 라디오쇼 정치시그널 (유튜브 라이브)\n08시 50분 김진의 돌직구 쇼\n10시 20분 김진의 더라방 (유튜브 라이브)\n12시 00분 뉴스A 라이브\n15시 50분 강력한 4팀\n17시 20분 뉴스TOP10\n19시 00분 뉴스A\n\n〈주말〉\n12시 00분 토요랭킹쇼·뉴스A 라이브\n17시 40분 뉴스TOP10\n19시 00분 뉴스A\n\n# # #채널A뉴스 \n\n▷ 홈페이지 http://www.ichannela.com/news/main/news_main.do\n▷ 페이스북 https://www.facebook.com/channelanews\n▷ 카카오스토리 https://story.kakao.com/ch/channelanews",
      "publishedAt": "2014-10-01T00:12:34Z",
      "duration": "PT12M3S",
      "viewCount": 10635,
      "likeCount": 37,
      "commentCount": 25,
      "tags": [
        "쾌도난마",
        "하종대의쾌도난마",
        "정치",
        "경제",
        "시사",
        "시사토크쇼",
        "박근혜",
        "대통령",
        "박대통령",
        "청와대",
        "담판",
        "사색변론",
        "북한25시",
        "맞수",
        "채널에이",
        "채널A",
        "공무원",
        "연금",
        "개혁안",
        "공무원연금",
        "공무원연금개혁안",
        "퇴직",
        "명퇴",
        "명예퇴직",
        "공무원명퇴"
      ],
      "liveBroadcastContent": "none",
      "liveStreamingDetails": null,
      "actualPubAt": "2014-10-01T00:12:34Z",
      "channelId": "UCfq4V1DAuaojnr2ryvWNysw",
      "channelName": "채널A News",
      "collectedAt": "2025-08-26T12:50:28Z"
    },
    "BY5rg8SrbdU": {
      "videoId": "BY5rg8SrbdU",
      "title": "홍도 유람선 구조 일등 공신은 홍도 주민들?_채널A_쾌도난마 704회",
      "description": "공식홈페이지 : http://tv.ichannela.com/culture/sisatalk\n[하종대의 쾌도난마] 14/09/30 방송 704회\n\n[2014.09.30]\n진춘택 SSU 해난구조대 상임위원, 김현 해상법 전문 변호사, 황태순 정치평론가, 이청 前 한강유람선 선장\n\n홍도 유람선 '전원구조'… 어떻게 가능했나?\n\n승객 104명 탑승, 승무원은 5명뿐… 문제없나?\n좌초된 홍도 유람선, 27년 전 일본에서 건조\n홍도 유람선 좌초… \"주민 대응 빛났다\"\n\n홍도 이장 \"사고 나면 5분 이내 출동한다\"\n홍도 유람선 구조 일등 공신은 홍도 주민들? ○ 기사 보기\n\n▶채널A뉴스 구독\nhttps://www.youtube.com/tvchanews?sub_confirmation=1\n\n[채널A 뉴스·시사 프로그램｜유튜브 라이브 방송시간]\n\n〈평일〉\n08시 00분 라디오쇼 정치시그널 (유튜브 라이브)\n08시 50분 김진의 돌직구 쇼\n10시 20분 김진의 더라방 (유튜브 라이브)\n12시 00분 뉴스A 라이브\n15시 50분 강력한 4팀\n17시 20분 뉴스TOP10\n19시 00분 뉴스A\n\n〈주말〉\n12시 00분 토요랭킹쇼·뉴스A 라이브\n17시 40분 뉴스TOP10\n19시 00분 뉴스A\n\n# # #채널A뉴스 \n\n▷ 홈페이지 http://www.ichannela.com/news/main/news_main.do\n▷ 페이스북 https://www.facebook.com/channelanews\n▷ 카카오스토리 https://story.kakao.com/ch/channelanews",
      "publishedAt": "2014-10-01T00:11:06Z",
      "duration": "PT5M28S",
      "viewCount": 523,
      "likeCount": 2,
      "commentCount": 0,
      "tags": [
        "쾌도난마",
        "하종대의쾌도난마",
        "정치",
        "경제",
        "시사",
        "시사토크쇼",
        "박근혜",
        "대통령",
        "박대통령",
        "청와대",
        "담판",
        "사색변론",
        "북한25시",
        "맞수",
        "채널에이",
        "채널A",
        "홍도",
        "유람선",
        "홍도유람선",
        "좌초",
        "선플라워호",
        "썬플라워호",
        "바캉스호",
        "세월호",
        "세월호참사",
        "세월호법"
      ],
      "liveBroadcastContent": "none",
      "liveStreamingDetails": null,
      "actualPubAt": "2014-10-01T00:11:06Z",
      "channelId": "UCfq4V1DAuaojnr2ryvWNysw",
      "channelName": "채널A News",
      "collectedAt": "2025-08-26T12:50:28Z"
    },
    "3ZZx4DECRKY": {
      "videoId": "3ZZx4DECRKY",
      "title": "홍도 유람선, 주민 반대 무릅쓰고 운항했다?_채널A_쾌도난마 704회",
      "description": "공식홈페이지 : http://tv.ichannela.com/culture/sisatalk\n[하종대의 쾌도난마] 14/09/30 방송 704회\n\n[2014.09.30]\n진춘택 SSU 해난구조대 상임위원, 김현 해상법 전문 변호사, 황태순 정치평론가, 이청 前 한강유람선 선장\n\n오늘 오전 홍도 유람선 좌초… 사고 경위는?\n\n27년 된 유람선… 노후 선박 운항에 문제없었나?\n홍도 주민들 \"노후 선박 좌초, 예견된 사고\"\n홍도 유람선, 주민 반대 무릅쓰고 운항했다?\n홍도 유람선 대표 \"사고 원인, 선장의 항로 이탈\" ○ 기사 보기\n\n▶채널A뉴스 구독\nhttps://www.youtube.com/tvchanews?sub_confirmation=1\n\n[채널A 뉴스·시사 프로그램｜유튜브 라이브 방송시간]\n\n〈평일〉\n08시 00분 라디오쇼 정치시그널 (유튜브 라이브)\n08시 50분 김진의 돌직구 쇼\n10시 20분 김진의 더라방 (유튜브 라이브)\n12시 00분 뉴스A 라이브\n15시 50분 강력한 4팀\n17시 20분 뉴스TOP10\n19시 00분 뉴스A\n\n〈주말〉\n12시 00분 토요랭킹쇼·뉴스A 라이브\n17시 40분 뉴스TOP10\n19시 00분 뉴스A\n\n# # #채널A뉴스 \n\n▷ 홈페이지 http://www.ichannela.com/news/main/news_main.do\n▷ 페이스북 https://www.facebook.com/channelanews\n▷ 카카오스토리 https://story.kakao.com/ch/channelanews",
      "publishedAt": "2014-10-01T00:11:03Z",
      "duration": "PT7M2S",
      "viewCount": 373,
      "likeCount": 3,
      "commentCount": 0,
      "tags": [
        "쾌도난마",
        "하종대의쾌도난마",
        "정치",
        "경제",
        "시사",
        "시사토크쇼",
        "박근혜",
        "대통령",
        "박대통령",
        "청와대",
        "담판",
        "사색변론",
        "북한25시",
        "맞수",
        "채널에이",
        "채널A",
        "홍도",
        "유람선",
        "홍도유람선",
        "좌초",
        "선플라워호",
        "썬플라워호",
        "바캉스호",
        "세월호",
        "세월호참사",
        "세월호법"
      ],
      "liveBroadcastContent": "none",
      "liveStreamingDetails": null,
      "actualPubAt": "2014-10-01T00:11:03Z",
      "channelId": "UCfq4V1DAuaojnr2ryvWNysw",
      "channelName": "채널A News",
      "collectedAt": "2025-08-26T12:50:28Z"
    },
    "aKUcTkHGbmU": {
      "videoId": "aKUcTkHGbmU",
      "title": "정부, '공무원 연금 개혁' 겁만 주고 실행 못한다?_채널A_쾌도난마 704회",
      "description": "공식홈페이지 : http://tv.ichannela.com/culture/sisatalk\n[하종대의 쾌도난마] 14/09/30 방송 704회\n\n[2014.09.30]\n김용하 前 한국연금학회 전 회장, 윤석명 한국보건사회연구원\n\n공무원연금 개혁방안 '당정 미루기' 논란\n공무원연금 반발 감안하더라도 개혁 불가피? ○ 기사 보기\n\n▶채널A뉴스 구독\nhttps://www.youtube.com/tvchanews?sub_confirmation=1\n\n[채널A 뉴스·시사 프로그램｜유튜브 라이브 방송시간]\n\n〈평일〉\n08시 00분 라디오쇼 정치시그널 (유튜브 라이브)\n08시 50분 김진의 돌직구 쇼\n10시 20분 김진의 더라방 (유튜브 라이브)\n12시 00분 뉴스A 라이브\n15시 50분 강력한 4팀\n17시 20분 뉴스TOP10\n19시 00분 뉴스A\n\n〈주말〉\n12시 00분 토요랭킹쇼·뉴스A 라이브\n17시 40분 뉴스TOP10\n19시 00분 뉴스A\n\n# # #채널A뉴스 \n\n▷ 홈페이지 http://www.ichannela.com/news/main/news_main.do\n▷ 페이스북 https://www.facebook.com/channelanews\n▷ 카카오스토리 https://story.kakao.com/ch/channelanews",
      "publishedAt": "2014-10-01T00:10:53Z",
      "duration": "PT1M25S",
      "viewCount": 372,
      "likeCount": 0,
      "commentCount": 0,
      "tags": [
        "쾌도난마",
        "하종대의쾌도난마",
        "정치",
        "경제",
        "시사",
        "시사토크쇼",
        "박근혜",
        "대통령",
        "박대통령",
        "청와대",
        "담판",
        "사색변론",
        "북한25시",
        "맞수",
        "채널에이",
        "채널A",
        "공무원",
        "연금",
        "개혁안",
        "공무원연금",
        "공무원연금개혁안",
        "퇴직",
        "명퇴",
        "명예퇴직",
        "공무원명퇴"
      ],
      "liveBroadcastContent": "none",
      "liveStreamingDetails": null,
      "actualPubAt": "2014-10-01T00:10:53Z",
      "channelId": "UCfq4V1DAuaojnr2ryvWNysw",
      "channelName": "채널A News",
      "collectedAt": "2025-08-26T12:50:28Z"
    },
    "WtWaOtCfu24": {
      "videoId": "WtWaOtCfu24",
      "title": "홍도 유람선 사건으로 해경 해체 살아날까?_채널A_쾌도난마 704회",
      "description": "공식홈페이지 : http://tv.ichannela.com/culture/sisatalk\n[하종대의 쾌도난마] 14/09/30 방송 704회\n\n[2014.09.30]\n진춘택 SSU 해난구조대 상임위원, 김현 해상법 전문 변호사, 황태순 정치평론가, 이청 前 한강유람선 선장\n\n홍도 유람선 '전원구조'… 해경 해체 반대에 힘 실릴까?\n홍도 유람선 '전원구조'… 해경 해체 반대 움직임?\n\n이병석 의원 \"해경 해체 사려깊지 못해\"\n與, 이병석 해경 해체 반대 \"공론의 장 필요\"\n\n해양안전 강화… 어떤 노력 추가 돼야 할까?\n'썬플라워호' 선장, 좌초 유람선 승객 80여 명 구조 ○ 기사 보기\n\n▶채널A뉴스 구독\nhttps://www.youtube.com/tvchanews?sub_confirmation=1\n\n[채널A 뉴스·시사 프로그램｜유튜브 라이브 방송시간]\n\n〈평일〉\n08시 00분 라디오쇼 정치시그널 (유튜브 라이브)\n08시 50분 김진의 돌직구 쇼\n10시 20분 김진의 더라방 (유튜브 라이브)\n12시 00분 뉴스A 라이브\n15시 50분 강력한 4팀\n17시 20분 뉴스TOP10\n19시 00분 뉴스A\n\n〈주말〉\n12시 00분 토요랭킹쇼·뉴스A 라이브\n17시 40분 뉴스TOP10\n19시 00분 뉴스A\n\n# # #채널A뉴스 \n\n▷ 홈페이지 http://www.ichannela.com/news/main/news_main.do\n▷ 페이스북 https://www.facebook.com/channelanews\n▷ 카카오스토리 https://story.kakao.com/ch/channelanews",
      "publishedAt": "2014-10-01T00:10:40Z",
      "duration": "PT3M27S",
      "viewCount": 371,
      "likeCount": 0,
      "commentCount": 0,
      "tags": [
        "쾌도난마",
        "하종대의쾌도난마",
        "정치",
        "경제",
        "시사",
        "시사토크쇼",
        "박근혜",
        "대통령",
        "박대통령",
        "청와대",
        "담판",
        "사색변론",
        "북한25시",
        "맞수",
        "채널에이",
        "채널A",
        "홍도",
        "유람선",
        "홍도유람선",
        "좌초",
        "선플라워호",
        "썬플라워호",
        "세월호",
        "세월호참사",
        "세월호법",
        "해경",
        "해경해체"
      ],
      "liveBroadcastContent": "none",
      "liveStreamingDetails": null,
      "actualPubAt": "2014-10-01T00:10:40Z",
      "channelId": "UCfq4V1DAuaojnr2ryvWNysw",
      "channelName": "채널A News",
      "collectedAt": "2025-08-26T12:50:28Z"
    },
    "ziZm0frXccg": {
      "videoId": "ziZm0frXccg",
      "title": "공무원 연금 개혁에 공무원 명퇴는 손해다?_채널A_쾌도난마 704회",
      "description": "공식홈페이지 : http://tv.ichannela.com/culture/sisatalk\n[하종대의 쾌도난마] 14/09/30 방송 704회\n\n[2014.09.30]\n김용하 前 한국연금학회 전 회장, 윤석명 한국보건사회연구원\n\n연금개혁 '벌벌'… 공무원 명퇴 급증\n올해 8876명 공무원 명퇴 러시… \"연금 깎일라\"\n\n당·정·청 \"공무원연금 정부최종안 10월 중순 마련\"\n당정청, 공무원연금 개혁 주체 떠넘기기… 입장은?\n안행부 \"깎인 공무원 연금, 급여 등으로 보상 고려\" ○ 기사 보기\n\n▶채널A뉴스 구독\nhttps://www.youtube.com/tvchanews?sub_confirmation=1\n\n[채널A 뉴스·시사 프로그램｜유튜브 라이브 방송시간]\n\n〈평일〉\n08시 00분 라디오쇼 정치시그널 (유튜브 라이브)\n08시 50분 김진의 돌직구 쇼\n10시 20분 김진의 더라방 (유튜브 라이브)\n12시 00분 뉴스A 라이브\n15시 50분 강력한 4팀\n17시 20분 뉴스TOP10\n19시 00분 뉴스A\n\n〈주말〉\n12시 00분 토요랭킹쇼·뉴스A 라이브\n17시 40분 뉴스TOP10\n19시 00분 뉴스A\n\n# # #채널A뉴스 \n\n▷ 홈페이지 http://www.ichannela.com/news/main/news_main.do\n▷ 페이스북 https://www.facebook.com/channelanews\n▷ 카카오스토리 https://story.kakao.com/ch/channelanews",
      "publishedAt": "2014-10-01T00:10:21Z",
      "duration": "PT3M20S",
      "viewCount": 2627,
      "likeCount": 6,
      "commentCount": 1,
      "tags": [
        "쾌도난마",
        "하종대의쾌도난마",
        "정치",
        "경제",
        "시사",
        "시사토크쇼",
        "박근혜",
        "대통령",
        "박대통령",
        "청와대",
        "담판",
        "사색변론",
        "북한25시",
        "맞수",
        "채널에이",
        "채널A",
        "공무원",
        "연금",
        "개혁안",
        "공무원연금",
        "공무원연금개혁안",
        "퇴직",
        "명퇴",
        "명예퇴직",
        "공무원명퇴"
      ],
      "liveBroadcastContent": "none",
      "liveStreamingDetails": null,
      "actualPubAt": "2014-10-01T00:10:21Z",
      "channelId": "UCfq4V1DAuaojnr2ryvWNysw",
      "channelName": "채널A News",
      "collectedAt": "2025-08-26T12:50:28Z"
    },
    "aCsiwznzvn0": {
      "videoId": "aCsiwznzvn0",
      "title": "홍도 유람선 좌초, 사건 발생부터 대응까지_채널A_쾌도난마 704회",
      "description": "공식홈페이지 : http://tv.ichannela.com/culture/sisatalk\n[하종대의 쾌도난마] 14/09/30 방송 704회\n\n[2014.09.30]\n진춘택 SSU 해난구조대 상임위원, 김현 해상법 전문 변호사, 황태순 정치평론가, 이청 前 한강유람선 선장\n\n홍도 유람선 '전원구조'… 어떻게 가능했나?\n홍도 유람선 구조 일등 공신은 홍도 주민들?\n'썬플라워호' 선장, 좌초 유람선 승객 80여 명 구조\n유람선 좌초 신고자 \"119는 불통, 112는 감도 나빠\"\n홍도 유람선 '전원구조'… 세월호 참사 학습효과? ○ 기사 보기\n\n▶채널A뉴스 구독\nhttps://www.youtube.com/tvchanews?sub_confirmation=1\n\n[채널A 뉴스·시사 프로그램｜유튜브 라이브 방송시간]\n\n〈평일〉\n08시 00분 라디오쇼 정치시그널 (유튜브 라이브)\n08시 50분 김진의 돌직구 쇼\n10시 20분 김진의 더라방 (유튜브 라이브)\n12시 00분 뉴스A 라이브\n15시 50분 강력한 4팀\n17시 20분 뉴스TOP10\n19시 00분 뉴스A\n\n〈주말〉\n12시 00분 토요랭킹쇼·뉴스A 라이브\n17시 40분 뉴스TOP10\n19시 00분 뉴스A\n\n# # #채널A뉴스 \n\n▷ 홈페이지 http://www.ichannela.com/news/main/news_main.do\n▷ 페이스북 https://www.facebook.com/channelanews\n▷ 카카오스토리 https://story.kakao.com/ch/channelanews",
      "publishedAt": "2014-10-01T00:06:04Z",
      "duration": "PT5M6S",
      "viewCount": 506,
      "likeCount": 0,
      "commentCount": 0,
      "tags": [
        "쾌도난마",
        "하종대의쾌도난마",
        "정치",
        "경제",
        "시사",
        "시사토크쇼",
        "박근혜",
        "대통령",
        "박대통령",
        "청와대",
        "담판",
        "사색변론",
        "북한25시",
        "맞수",
        "채널에이",
        "채널A",
        "홍도",
        "유람선",
        "홍도유람선",
        "좌초",
        "선플라워호",
        "썬플라워호",
        "바캉스호",
        "세월호",
        "세월호참사",
        "세월호법"
      ],
      "liveBroadcastContent": "none",
      "liveStreamingDetails": null,
      "actualPubAt": "2014-10-01T00:06:04Z",
      "channelId": "UCfq4V1DAuaojnr2ryvWNysw",
      "channelName": "채널A News",
      "collectedAt": "2025-08-26T12:50:28Z"
    },
    "ysdrcJfi9aU": {
      "videoId": "ysdrcJfi9aU",
      "title": "소 잃고 외양간 고친 ‘홍도 유람선 좌초’?_채널A_쾌도난마 704회",
      "description": "공식홈페이지 : http://tv.ichannela.com/culture/sisatalk\n[하종대의 쾌도난마] 14/09/30 방송 704회\n\n[2014.09.30]\n오늘 오전 발생한 홍도 유람선 좌초 사고의 최초 신고자가 전한 사고 당시의 상황은 '혼란' 그 자체였습니다. 설상가상, 구명조끼는 입을 수 없을 정도로 불량 상태였다고 합니다.\n\n사고 선박은 87년 건조돼 세월호보다 7년이나 더 낡은 배로 운항 허가 당시 홍도 주민의 반발을 사기도 했답니다. 다행히 홍도의 해경과 주민, 선원들이 재빨리 대처해 인명피해는 없었지만, 세월호 참사가 발생한 지 5개월이 지나도록 소 잃고 외양간도 제대로 못 고쳤으니 한심합니다.\n\n여전히 표류 중인 세월호법만 봐도 그렇습니다. 이러고도 ‘제2의 세월호 참사’가 일어나지 않는다는 확신을, 그 누가 할 수 있을지, 냉정하게 되짚어봐야 할 때입니다. ○ 기사 보기\n\n▶채널A뉴스 구독\nhttps://www.youtube.com/tvchanews?sub_confirmation=1\n\n[채널A 뉴스·시사 프로그램｜유튜브 라이브 방송시간]\n\n〈평일〉\n08시 00분 라디오쇼 정치시그널 (유튜브 라이브)\n08시 50분 김진의 돌직구 쇼\n10시 20분 김진의 더라방 (유튜브 라이브)\n12시 00분 뉴스A 라이브\n15시 50분 강력한 4팀\n17시 20분 뉴스TOP10\n19시 00분 뉴스A\n\n〈주말〉\n12시 00분 토요랭킹쇼·뉴스A 라이브\n17시 40분 뉴스TOP10\n19시 00분 뉴스A\n\n# # #채널A뉴스 \n\n▷ 홈페이지 http://www.ichannela.com/news/main/news_main.do\n▷ 페이스북 https://www.facebook.com/channelanews\n▷ 카카오스토리 https://story.kakao.com/ch/channelanews",
      "publishedAt": "2014-10-01T00:05:53Z",
      "duration": "PT1M6S",
      "viewCount": 488,
      "likeCount": 0,
      "commentCount": 1,
      "tags": [
        "쾌도난마",
        "하종대의쾌도난마",
        "정치",
        "경제",
        "시사",
        "시사토크쇼",
        "박근혜",
        "대통령",
        "박대통령",
        "청와대",
        "담판",
        "사색변론",
        "북한25시",
        "맞수",
        "채널에이",
        "채널A",
        "홍도",
        "유람선",
        "홍도유람선",
        "좌초",
        "세월호",
        "세월호참사",
        "세월호법"
      ],
      "liveBroadcastContent": "none",
      "liveStreamingDetails": null,
      "actualPubAt": "2014-10-01T00:05:53Z",
      "channelId": "UCfq4V1DAuaojnr2ryvWNysw",
      "channelName": "채널A News",
      "collectedAt": "2025-08-26T12:50:28Z"
    },
    "rl_1xz463VY": {
      "videoId": "rl_1xz463VY",
      "title": "일반인 유가족, 영정 회수하고 고소장 제출하고_채널A_시사병법 109회",
      "description": "공식홈페이지 : http://tv.ichannela.com/sisa/strategy \n[정용관의 시사병법] 14/09/30 방송 109회\n\n[2014.09.30]\n출연: 변환봉 변호사, 임방글 변호사, 윤주진 자유공방 대표, 동정민 채널A 정치부 기자\n\n일반인 유가족, 안산 합동분향소에서 영정 회수\n단원고 유가족 \"영정 당장 가져가라 밖에 던져 버리겠다\"\n일반인 유가족, 유경근 대변인 명예훼손으로 고소 예정\n\n일반인 유가족 \"거짓말 사과 않는 이들과 함께 못 있어\"\n일부 단원고 유가족, 일반인 유가족 향해 고함 질러\n\n고소 고발전으로 비화한 세월호 사건, 어떻게 보나?\n\"국회가 갈등 해결 못해 세월호 사건, 고소고발전 비화\"\n\n세월호 특별법, 박 대통령 개입해야 하나?\n\n\n[정용관의 시사병법]\n매주 월~금 오후 3시 50분 방송 ○ 기사 보기\n\n▶채널A뉴스 구독\nhttps://www.youtube.com/tvchanews?sub_confirmation=1\n\n[채널A 뉴스·시사 프로그램｜유튜브 라이브 방송시간]\n\n〈평일〉\n08시 00분 라디오쇼 정치시그널 (유튜브 라이브)\n08시 50분 김진의 돌직구 쇼\n10시 20분 김진의 더라방 (유튜브 라이브)\n12시 00분 뉴스A 라이브\n15시 50분 강력한 4팀\n17시 20분 뉴스TOP10\n19시 00분 뉴스A\n\n〈주말〉\n12시 00분 토요랭킹쇼·뉴스A 라이브\n17시 40분 뉴스TOP10\n19시 00분 뉴스A\n\n# # #채널A뉴스 \n\n▷ 홈페이지 http://www.ichannela.com/news/main/news_main.do\n▷ 페이스북 https://www.facebook.com/channelanews\n▷ 카카오스토리 https://story.kakao.com/ch/channelanews",
      "publishedAt": "2014-10-01T01:08:48Z",
      "duration": "PT8M10S",
      "viewCount": 703,
      "likeCount": 1,
      "commentCount": 0,
      "tags": [
        "정용관",
        "시사병법",
        "정용관의시사병법",
        "정용관정치부장",
        "채널a정치부장",
        "변환봉 변호사",
        "임방글 변호사",
        "동정민 기자",
        "윤주진 대표",
        "자유공방",
        "일반인 유가족",
        "영정 회수",
        "유경근 명예훼손",
        "유경근 고소",
        "단원고 유가족",
        "세월호 특별법"
      ],
      "liveBroadcastContent": "none",
      "liveStreamingDetails": null,
      "actualPubAt": "2014-10-01T01:08:48Z",
      "channelId": "UCfq4V1DAuaojnr2ryvWNysw",
      "channelName": "채널A News",
      "collectedAt": "2025-08-26T12:50:28Z"
    },
    "SqkPcLEnSyI": {
      "videoId": "SqkPcLEnSyI",
      "title": "대리기사 입장과 다른 김현 해명, 정황 봤더니_채널A_시사병법 109회",
      "description": "공식홈페이지 : http://tv.ichannela.com/sisa/strategy \n[정용관의 시사병법] 14/09/30 방송 109회\n\n[2014.09.30]\n출연: 변환봉 변호사, 임방글 변호사, 윤주진 자유공방 대표, 동정민 채널A 정치부 기자\n\n朴 대통령 \"개혁, 거창한 구호가 중요한 것 아냐\"\n\n박영선 중재안 \"특검 후보 추천도 유가족 동의\" \n\n이완구 \"세월호 유가족과 협상하는 것 아냐\"\n이완구 \"유가족이 박영선 대표에게 권한 위임해야\"\n전명선 \"전권 위임은 유족에 대한 언어탄압\"\n\n대리운전사 측 \"김현, 상황 빠져나갈 궁리만 한다\"\n김현 해명, 대리운전사 입장과 달라… 진실은?\n\n김현, 새정치연합 의원들에게 '사과 편지'\n김현 \"유가족 진정시키려 노력했다\"\n\n김현 \"이 씨가 명함 달라기에 줬던 것 뿐\"\n김현 \"나와 떨어진 곳에서 사건 발생… 현장 못 봐\"\n\n조경태 \"김현, 읍참마속의 심정으로 출당시켜야\"\n정청래 \"새누리 정신적 당원 조경태 최저의원 출당해야\"\n\n'乙을 위한 정당' 만든다더니… '김현 감싸기' 왜?\n옹호하거나 함구하거나… 새정치연합, 김현 감싸기?\n문재인 \"주제하고는 상관 없죠. 다른 이야기 분산 말아야\"\n\n\n[정용관의 시사병법]\n매주 월~금 오후 3시 50분 방송 ○ 기사 보기\n\n▶채널A뉴스 구독\nhttps://www.youtube.com/tvchanews?sub_confirmation=1\n\n[채널A 뉴스·시사 프로그램｜유튜브 라이브 방송시간]\n\n〈평일〉\n08시 00분 라디오쇼 정치시그널 (유튜브 라이브)\n08시 50분 김진의 돌직구 쇼\n10시 20분 김진의 더라방 (유튜브 라이브)\n12시 00분 뉴스A 라이브\n15시 50분 강력한 4팀\n17시 20분 뉴스TOP10\n19시 00분 뉴스A\n\n〈주말〉\n12시 00분 토요랭킹쇼·뉴스A 라이브\n17시 40분 뉴스TOP10\n19시 00분 뉴스A\n\n# # #채널A뉴스 \n\n▷ 홈페이지 http://www.ichannela.com/news/main/news_main.do\n▷ 페이스북 https://www.facebook.com/channelanews\n▷ 카카오스토리 https://story.kakao.com/ch/channelanews",
      "publishedAt": "2014-10-01T01:08:18Z",
      "duration": "PT17M29S",
      "viewCount": 2166,
      "likeCount": 6,
      "commentCount": 0,
      "tags": [
        "채널A",
        "채널A스포츠뉴스"
      ],
      "liveBroadcastContent": "none",
      "liveStreamingDetails": null,
      "actualPubAt": "2014-10-01T01:08:18Z",
      "channelId": "UCfq4V1DAuaojnr2ryvWNysw",
      "channelName": "채널A News",
      "collectedAt": "2025-08-26T12:50:28Z"
    },
    "5YL8iQuaeIg": {
      "videoId": "5YL8iQuaeIg",
      "title": "세월호보다 노후한 홍도 유람선…주민 반대 있었다_채널A_시사병법 109회",
      "description": "공식홈페이지 : http://tv.ichannela.com/sisa/strategy \n[정용관의 시사병법] 14/09/30 방송 109회\n\n[2014.09.30]\n출연: 변환봉 변호사, 임방글 변호사, 윤주진 자유공방 대표, 동정민 채널A 정치부 기자\n\n홍도 유람선 좌초… \"주민들 배 20여 척 몰고 구조\"\n\n바캉스호… 일본에서 수입된 선령 27년의 노후 선박\n1987년 건조된 바캉스호, 주민 반대에도 운항\n\n홍도 유람선 좌초, 탑승객 110명 전원 구조\n홍도 주민들 \"바캉스호 허가 내주지 말라\" 해경 청원\n탑승객 \"119는 불통, 112는 위치만 물어\"\n\n\n[정용관의 시사병법]\n매주 월~금 오후 3시 50분 방송 ○ 기사 보기\n\n▶채널A뉴스 구독\nhttps://www.youtube.com/tvchanews?sub_confirmation=1\n\n[채널A 뉴스·시사 프로그램｜유튜브 라이브 방송시간]\n\n〈평일〉\n08시 00분 라디오쇼 정치시그널 (유튜브 라이브)\n08시 50분 김진의 돌직구 쇼\n10시 20분 김진의 더라방 (유튜브 라이브)\n12시 00분 뉴스A 라이브\n15시 50분 강력한 4팀\n17시 20분 뉴스TOP10\n19시 00분 뉴스A\n\n〈주말〉\n12시 00분 토요랭킹쇼·뉴스A 라이브\n17시 40분 뉴스TOP10\n19시 00분 뉴스A\n\n# # #채널A뉴스 \n\n▷ 홈페이지 http://www.ichannela.com/news/main/news_main.do\n▷ 페이스북 https://www.facebook.com/channelanews\n▷ 카카오스토리 https://story.kakao.com/ch/channelanews",
      "publishedAt": "2014-10-01T01:07:26Z",
      "duration": "PT5M48S",
      "viewCount": 822,
      "likeCount": 0,
      "commentCount": 0,
      "tags": [
        "정용관",
        "시사병법",
        "정용관의시사병법",
        "정용관정치부장",
        "채널a정치부장",
        "변환봉 변호사",
        "임방글 변호사",
        "동정민 기자",
        "윤주진 대표",
        "자유공방",
        "바캉스호",
        "홍도 유람선 좌초",
        "홍도 유람선",
        "바캉스호 좌초"
      ],
      "liveBroadcastContent": "none",
      "liveStreamingDetails": null,
      "actualPubAt": "2014-10-01T01:07:26Z",
      "channelId": "UCfq4V1DAuaojnr2ryvWNysw",
      "channelName": "채널A News",
      "collectedAt": "2025-08-26T12:50:28Z"
    },
    "DZMEoCpD4Gk": {
      "videoId": "DZMEoCpD4Gk",
      "title": "김정은 잠적 27일째…파리서 김정남 포착_채널A_시사병법 109회",
      "description": "공식홈페이지 : http://tv.ichannela.com/sisa/strategy \n[정용관의 시사병법] 14/09/30 방송 109회\n\n[2014.09.30]\n출연: 김정안 동아일보 정치부 기자\n\n김정은 이복형 김정남, 파리에 나타난 이유는?\n김정남 파리서 목격… 유학온 아들 만나러온 듯\n\n김정은 은둔 27일째… 정변설에 위중설까지\n중국 SNS '웨이보', 조명록 군사정변설 나돌아\n조명록 전 총정치국장 2010년 사망… 군사정변은 낭설?\n미 국무부 '김정은 신변이상설'에 \"노코멘트\"\n\n김정남, 파리 르메르디앙 에투알 호텔에 머물러\n김정남, 30대 여성과 함께 아침식사하는 모습 포착\n김정남, 1월 쿠알라룸푸르, 5월 자카르타에서도 목격\n\n김정남 아들 김한솔이 다니는 파리정치대학은?  \n\n김정남, 장성택 질문에 입술 깨물며 \"할 말 없다\"\n김정남 \"(장성택 사건) 정말 할 말 없다. 그만하자\"\n\n김정남, 북한의 권력 핵심에 들어설 가능성 있나?\n\n[정용관의 시사병법]\n매주 월~금 오후 3시 50분 방송 ○ 기사 보기\n\n▶채널A뉴스 구독\nhttps://www.youtube.com/tvchanews?sub_confirmation=1\n\n[채널A 뉴스·시사 프로그램｜유튜브 라이브 방송시간]\n\n〈평일〉\n08시 00분 라디오쇼 정치시그널 (유튜브 라이브)\n08시 50분 김진의 돌직구 쇼\n10시 20분 김진의 더라방 (유튜브 라이브)\n12시 00분 뉴스A 라이브\n15시 50분 강력한 4팀\n17시 20분 뉴스TOP10\n19시 00분 뉴스A\n\n〈주말〉\n12시 00분 토요랭킹쇼·뉴스A 라이브\n17시 40분 뉴스TOP10\n19시 00분 뉴스A\n\n# # #채널A뉴스 \n\n▷ 홈페이지 http://www.ichannela.com/news/main/news_main.do\n▷ 페이스북 https://www.facebook.com/channelanews\n▷ 카카오스토리 https://story.kakao.com/ch/channelanews",
      "publishedAt": "2014-10-01T01:07:04Z",
      "duration": "PT13M11S",
      "viewCount": 9675,
      "likeCount": 9,
      "commentCount": 2,
      "tags": [
        "정용관",
        "시사병법",
        "정용관의시사병법",
        "정용관정치부장",
        "채널a정치부장",
        "김정안 기자",
        "김정은 잠적",
        "김정은 은둔",
        "김정남 파리",
        "김정남 아들",
        "김한솔",
        "김한솔 파리정치대학",
        "김정남 호텔",
        "조명록 정변설",
        "북한 정변설",
        "김정은 위중설"
      ],
      "liveBroadcastContent": "none",
      "liveStreamingDetails": null,
      "actualPubAt": "2014-10-01T01:07:04Z",
      "channelId": "UCfq4V1DAuaojnr2ryvWNysw",
      "channelName": "채널A News",
      "collectedAt": "2025-08-26T12:50:28Z"
    },
    "-1xyleG3FpM": {
      "videoId": "-1xyleG3FpM",
      "title": "[단독]김정남 “건강? 아직 쓸 만해 보이지 않나”_채널A_뉴스TOP10",
      "description": "공식홈페이지 : http://news.ichannela.com/tv/NewsTOP10\n[뉴스TOP10] 14/09/30 방송 \n\n[단독]김정남 “건강? 아직 쓸 만해 보이지 않나”",
      "publishedAt": "2014-10-01T00:43:35Z",
      "duration": "PT5M32S",
      "viewCount": 672,
      "likeCount": 0,
      "commentCount": 0,
      "tags": [
        "채널에이",
        "채널A",
        "정치",
        "시사",
        "토크",
        "뉴스",
        "뉴스탑텐",
        "TOP10",
        "cosjfdpdl",
        "cosjfㅁ",
        "채넒",
        "channela",
        "cosjfa",
        "채널a 뉴스",
        "채널에이 뉴스",
        "채널a news",
        "channela news",
        "cosjfdpdlsbtm",
        "취재",
        "실시간",
        "news",
        "뉴스TOP10",
        "sbtm새ㅔ10",
        "sbtmxkqxps",
        "뉴스톱텐",
        "sbtmxhqxps",
        "톱텐",
        "xhqxps",
        "탑텐",
        "xkqxps",
        "top텐"
      ],
      "liveBroadcastContent": "none",
      "liveStreamingDetails": null,
      "actualPubAt": "2014-10-01T00:43:35Z",
      "channelId": "UCfq4V1DAuaojnr2ryvWNysw",
      "channelName": "채널A News",
      "collectedAt": "2025-08-26T12:50:28Z"
    },
    "TpvhsDr5Ccg": {
      "videoId": "TpvhsDr5Ccg",
      "title": "뉴욕 막말 시위 주도인물, 北 김일성상 수상자_채널A_뉴스TOP10",
      "description": "공식홈페이지 : http://news.ichannela.com/tv/NewsTOP10\n[뉴스TOP10] 14/09/30 방송 \n\n뉴욕 막말 시위 주도인물, 北 김일성상 수상자",
      "publishedAt": "2014-10-01T00:43:53Z",
      "duration": "PT4M",
      "viewCount": 641,
      "likeCount": 1,
      "commentCount": 1,
      "tags": [
        "채널에이",
        "채널A",
        "정치",
        "시사",
        "토크",
        "뉴스",
        "뉴스탑텐",
        "TOP10",
        "cosjfdpdl",
        "cosjfㅁ",
        "채넒",
        "channela",
        "cosjfa",
        "채널a 뉴스",
        "채널에이 뉴스",
        "채널a news",
        "channela news",
        "cosjfdpdlsbtm",
        "취재",
        "실시간",
        "news",
        "뉴스TOP10",
        "sbtm새ㅔ10",
        "sbtmxkqxps",
        "뉴스톱텐",
        "sbtmxhqxps",
        "톱텐",
        "xhqxps",
        "탑텐",
        "xkqxps",
        "top텐"
      ],
      "liveBroadcastContent": "none",
      "liveStreamingDetails": null,
      "actualPubAt": "2014-10-01T00:43:53Z",
      "channelId": "UCfq4V1DAuaojnr2ryvWNysw",
      "channelName": "채널A News",
      "collectedAt": "2025-08-26T12:50:28Z"
    },
    "RrIHIYLijPc": {
      "videoId": "RrIHIYLijPc",
      "title": "소녀시대 “굿바이 제시카”…7년 만에 멤버 이탈_채널A_뉴스TOP10",
      "description": "공식홈페이지 : http://news.ichannela.com/tv/NewsTOP10\n[뉴스TOP10] 14/09/30 방송 \n\n소녀시대 “굿바이 제시카”…7년 만에 멤버 이탈",
      "publishedAt": "2014-10-01T00:44:06Z",
      "duration": "PT5M36S",
      "viewCount": 4107,
      "likeCount": 14,
      "commentCount": 2,
      "tags": [
        "채널에이",
        "채널A",
        "정치",
        "시사",
        "토크",
        "뉴스",
        "뉴스탑텐",
        "TOP10",
        "cosjfdpdl",
        "cosjfㅁ",
        "채넒",
        "channela",
        "cosjfa",
        "채널a 뉴스",
        "채널에이 뉴스",
        "채널a news",
        "channela news",
        "cosjfdpdlsbtm",
        "취재",
        "실시간",
        "news",
        "뉴스TOP10",
        "sbtm새ㅔ10",
        "sbtmxkqxps",
        "뉴스톱텐",
        "sbtmxhqxps",
        "톱텐",
        "xhqxps",
        "탑텐",
        "xkqxps",
        "top텐"
      ],
      "liveBroadcastContent": "none",
      "liveStreamingDetails": null,
      "actualPubAt": "2014-10-01T00:44:06Z",
      "channelId": "UCfq4V1DAuaojnr2ryvWNysw",
      "channelName": "채널A News",
      "collectedAt": "2025-08-26T12:50:28Z"
    },
    "0Tg9DLM1IOg": {
      "videoId": "0Tg9DLM1IOg",
      "title": "협상·번복·의총·재협상…롤러코스터 국회_채널A_뉴스TOP10",
      "description": "공식홈페이지 : http://news.ichannela.com/tv/NewsTOP10\n[뉴스TOP10] 14/09/30 방송 \n\n협상·번복·의총·재협상…롤러코스터 국회",
      "publishedAt": "2014-10-01T00:44:20Z",
      "duration": "PT12M27S",
      "viewCount": 291,
      "likeCount": 0,
      "commentCount": 0,
      "tags": [
        "채널에이",
        "채널A",
        "정치",
        "시사",
        "토크",
        "뉴스",
        "뉴스탑텐",
        "TOP10",
        "cosjfdpdl",
        "cosjfㅁ",
        "채넒",
        "channela",
        "cosjfa",
        "채널a 뉴스",
        "채널에이 뉴스",
        "채널a news",
        "channela news",
        "cosjfdpdlsbtm",
        "취재",
        "실시간",
        "news",
        "뉴스TOP10",
        "sbtm새ㅔ10",
        "sbtmxkqxps",
        "뉴스톱텐",
        "sbtmxhqxps",
        "톱텐",
        "xhqxps",
        "탑텐",
        "xkqxps",
        "top텐"
      ],
      "liveBroadcastContent": "none",
      "liveStreamingDetails": null,
      "actualPubAt": "2014-10-01T00:44:20Z",
      "channelId": "UCfq4V1DAuaojnr2ryvWNysw",
      "channelName": "채널A News",
      "collectedAt": "2025-08-26T12:50:28Z"
    },
    "JGUi3pZC1Og": {
      "videoId": "JGUi3pZC1Og",
      "title": "세월호 일반인 유족, 유경근 대변인 고소_채널A_뉴스TOP10",
      "description": "공식홈페이지 : http://news.ichannela.com/tv/NewsTOP10\n[뉴스TOP10] 14/09/30 방송 \n\n세월호 일반인 유족, 유경근 대변인 고소",
      "publishedAt": "2014-10-01T00:44:37Z",
      "duration": "PT6M8S",
      "viewCount": 476,
      "likeCount": 2,
      "commentCount": 0,
      "tags": [
        "채널에이",
        "채널A",
        "정치",
        "시사",
        "토크",
        "뉴스",
        "뉴스탑텐",
        "TOP10",
        "cosjfdpdl",
        "cosjfㅁ",
        "채넒",
        "channela",
        "cosjfa",
        "채널a 뉴스",
        "채널에이 뉴스",
        "채널a news",
        "channela news",
        "cosjfdpdlsbtm",
        "취재",
        "실시간",
        "news",
        "뉴스TOP10",
        "sbtm새ㅔ10",
        "sbtmxkqxps",
        "뉴스톱텐",
        "sbtmxhqxps",
        "톱텐",
        "xhqxps",
        "탑텐",
        "xkqxps",
        "top텐"
      ],
      "liveBroadcastContent": "none",
      "liveStreamingDetails": null,
      "actualPubAt": "2014-10-01T00:44:37Z",
      "channelId": "UCfq4V1DAuaojnr2ryvWNysw",
      "channelName": "채널A News",
      "collectedAt": "2025-08-26T12:50:28Z"
    },
    "Uwt4DLWzC7w": {
      "videoId": "Uwt4DLWzC7w",
      "title": "50억 걸고 ‘이병헌 낚기’…몰카·연출 드러나_채널A_뉴스TOP10",
      "description": "공식홈페이지 : http://news.ichannela.com/tv/NewsTOP10\n[뉴스TOP10] 14/09/30 방송 \n\n50억 걸고 ‘이병헌 낚기’…몰카·연출 드러나",
      "publishedAt": "2014-10-01T00:44:48Z",
      "duration": "PT5M38S",
      "viewCount": 5148,
      "likeCount": 1,
      "commentCount": 1,
      "tags": [
        "채널에이",
        "채널A",
        "정치",
        "시사",
        "토크",
        "뉴스",
        "뉴스탑텐",
        "TOP10",
        "cosjfdpdl",
        "cosjfㅁ",
        "채넒",
        "channela",
        "cosjfa",
        "채널a 뉴스",
        "채널에이 뉴스",
        "채널a news",
        "channela news",
        "cosjfdpdlsbtm",
        "취재",
        "실시간",
        "news",
        "뉴스TOP10",
        "sbtm새ㅔ10",
        "sbtmxkqxps",
        "뉴스톱텐",
        "sbtmxhqxps",
        "톱텐",
        "xhqxps",
        "탑텐",
        "xkqxps",
        "top텐"
      ],
      "liveBroadcastContent": "none",
      "liveStreamingDetails": null,
      "actualPubAt": "2014-10-01T00:44:48Z",
      "channelId": "UCfq4V1DAuaojnr2ryvWNysw",
      "channelName": "채널A News",
      "collectedAt": "2025-08-26T12:50:28Z"
    },
    "dMiS5rm3Z3s": {
      "videoId": "dMiS5rm3Z3s",
      "title": "홍도 유람선 좌초…신고 16분 만에 110명 구조_채널A_뉴스TOP10",
      "description": "공식홈페이지 : http://news.ichannela.com/tv/NewsTOP10\n[뉴스TOP10] 14/09/30 방송 \n\n홍도 유람선 좌초…신고 16분 만에 110명 구조",
      "publishedAt": "2014-10-01T00:45:01Z",
      "duration": "PT1M37S",
      "viewCount": 250,
      "likeCount": 0,
      "commentCount": 0,
      "tags": [
        "채널에이",
        "채널A",
        "정치",
        "시사",
        "토크",
        "뉴스",
        "뉴스탑텐",
        "TOP10",
        "cosjfdpdl",
        "cosjfㅁ",
        "채넒",
        "channela",
        "cosjfa",
        "채널a 뉴스",
        "채널에이 뉴스",
        "채널a news",
        "channela news",
        "cosjfdpdlsbtm",
        "취재",
        "실시간",
        "news",
        "뉴스TOP10",
        "sbtm새ㅔ10",
        "sbtmxkqxps",
        "뉴스톱텐",
        "sbtmxhqxps",
        "톱텐",
        "xhqxps",
        "탑텐",
        "xkqxps",
        "top텐"
      ],
      "liveBroadcastContent": "none",
      "liveStreamingDetails": null,
      "actualPubAt": "2014-10-01T00:45:01Z",
      "channelId": "UCfq4V1DAuaojnr2ryvWNysw",
      "channelName": "채널A News",
      "collectedAt": "2025-08-26T12:50:28Z"
    },
    "j6wmKhbspAk": {
      "videoId": "j6wmKhbspAk",
      "title": "탈북장교가 본 '한국 군' vs. '북한 군' / YTN",
      "description": "[YTN 기사원문] http://www.ytn.co.kr/_ln/0101_201410011400004089\n[앵커] 북한에서 장교로 10년 동안 근무했고 지금은 중위까지 올랐습니다.2006년에 탈북한 김정아 씨가 있습니다.이분이 한국 군대를 한번 꼭 체험을 하고 싶다는 생각을 늘 갖고 있었는데 얼마 전에 그래서 그 소원이 이루어져서 한국 군대를 직접 갔다왔다고 합니다.오늘 국군의 날 맞아서 김정아 씨를 저희가 초대했습니...",
      "publishedAt": "2014-10-01T06:23:12Z",
      "duration": "PT16M3S",
      "viewCount": 4944162,
      "likeCount": 18393,
      "commentCount": 1239,
      "tags": [
        "탈북",
        "YTN",
        "뉴스",
        "North Korea",
        "정치",
        "한국",
        "북한",
        "defector",
        "South Korea",
        "army"
      ],
      "liveBroadcastContent": "none",
      "liveStreamingDetails": null,
      "actualPubAt": "2014-10-01T06:23:12Z",
      "channelId": "UChlgI3UHCOnwUGzWzbJ3H5w",
      "channelName": " YTN",
      "collectedAt": "2025-08-27T19:04:10Z"
    },
    "AucGkVw4soo": {
      "videoId": "AucGkVw4soo",
      "title": "[아침신문 1면] 구제역 매몰지 인근 지하수, 병원성 오염 첫 확인 / YTN",
      "description": "[YTN 기사원문] http://www.ytn.co.kr/_ln/0103_201410010600420433\n[앵커]오늘 아침신문 1면 살펴보겠습니다.먼저 중앙일보입니다.부부가 이혼할 때 퇴직 연금은 어떻게 분할해야 하나, 대법원이 첫 판결을 내렸습니다.결과는, 전업주부라면 35%, 맞벌이를 했다면 50%의 비율로 퇴직 연금을 나눠야 한다고 판결했습니다.결혼기간, 재직 기간 등을 종합적으로 고려했다고 합니다.공무원 군인,...",
      "publishedAt": "2014-09-30T21:10:05Z",
      "duration": "PT2M49S",
      "viewCount": 501,
      "likeCount": 0,
      "commentCount": 1,
      "tags": [
        "YTN",
        "뉴스",
        "사회"
      ],
      "liveBroadcastContent": "none",
      "liveStreamingDetails": null,
      "actualPubAt": "2014-09-30T21:10:05Z",
      "channelId": "UChlgI3UHCOnwUGzWzbJ3H5w",
      "channelName": " YTN",
      "collectedAt": "2025-08-27T19:04:10Z"
    },
    "XF1qVGlExyc": {
      "videoId": "XF1qVGlExyc",
      "title": "[한국일보] 박일근 특파원, 홍콩 '우산 혁명' 현장을 가다",
      "description": "박일근 베이징 특파원이 홍콩 시위 현장을 찾았습니다. 2014년 10월 1일 홍콩 정부종합청사와 지하철 애드미럴티(金鐘)역 사이 금융 중심가에서 직접 촬영한 영상입니다. 영상 중 등장하는 두 여성은 시위대를 위해 생수 등을 나눠주는 자원봉사자 엠마 추이씨와 엘바 창씨로, \"우리는 진정한 직선제를 원한다\"고 말하고 있습니다.\n\nIl-Keun Park, a correspondent of The Hankookilbo, visited Hong Kong to report democracy protests. Two women in video, Emma Chui and Elva Chang, is saying \"we want true universal suffrage\". This video is recorded on October 1.",
      "publishedAt": "2014-10-01T10:10:14Z",
      "duration": "PT1M53S",
      "viewCount": 1317,
      "likeCount": 10,
      "commentCount": 0,
      "tags": [
        "홍콩",
        "우산혁명",
        "우산 혁명",
        "Hong Kong (Country)",
        "umbrella revollution"
      ],
      "liveBroadcastContent": "none",
      "liveStreamingDetails": null,
      "actualPubAt": "2014-10-01T10:10:14Z",
      "channelId": "UC1aS5CRRDrN6CmR2VcpmetA",
      "channelName": "한국일보(hankookilbo.com)",
      "collectedAt": "2025-09-03T10:02:02Z"
    },
    "Dd5B0T_11zY": {
      "videoId": "Dd5B0T_11zY",
      "title": "[이대근의 단언컨대]49회 북한을 미치게 하는 박근혜",
      "description": "",
      "publishedAt": "2014-10-01T12:36:42Z",
      "duration": "PT14M53S",
      "viewCount": 558,
      "likeCount": 4,
      "commentCount": 0,
      "tags": [
        "경향신문",
        "Park Geun-hye (Politician)",
        "Politics (TV Genre)"
      ],
      "liveBroadcastContent": "none",
      "liveStreamingDetails": null,
      "actualPubAt": "2014-10-01T12:36:42Z",
      "channelId": "UCHXvjavEtkPFJCfGlm0wTXw",
      "channelName": "경향티비",
      "collectedAt": "2025-09-03T10:02:02Z"
    },
    "eJkGbsujFr4": {
      "videoId": "eJkGbsujFr4",
      "title": "[경향신문]다음카카오 출범 기자회견",
      "description": "다음카카오(공동대표 최세훈, 이석우)가 합병을 완료하고 ‘모바일 라이프 플랫폼’ 기업으로 도약한다고 선언했다.\n다음카카오는 1일 서울 소공동 웨스틴조선호텔에서 개최된 다음카카오 데이원(Daum Kakao Day 1) 기자간담회에서 통합법인의 공식 출범을 발표했다. \n다음카카오는 지난 4개월간 합병을 이끌어온 최세훈, 이석우 공동대표 체제로 운영된다고 발표했다. 최 공동대표는 “다음카카오는 지금까지 인터넷과 모바일의 새로운 패러다임을 제시해온 경험을 바탕으로 시대적 요구에 부응하며 여러 파트너들과 함께 새롭게 도약할 것”이라며 “다음카카오가 만들어갈 혁신이 우리의 삶에 의미 있는 가치가 되기를 바란다”고 밝혔다.\n\n\n이 공동대표는 “우리가 살아가는 이 세상에는 사람, 정보, 사물, 프로세스 등 아직 연결되지 않은 많은 영역이 존재한다”며 “다음카카오는 우리 앞에 도래한 이 ‘연결의 세상’에서 사람과 사물을 아우르는 새로운 소통방식, 나아가 새로운 세상을 만들어나가는 미션에 도전할 것”이라고 강조했다.\n두 공동대표는 “‘새로운 연결, 새로운 세상(Connect Everything)’이라는 비전 하에 모바일 라이프 플랫폼 리더로서 다음카카오가 지금까지 없던 새로운 영역을 개척해 나갈 것”이라고 밝혔다.\n\n손봉석 기자",
      "publishedAt": "2014-10-01T06:05:02Z",
      "duration": "PT6M51S",
      "viewCount": 379,
      "likeCount": 1,
      "commentCount": 0,
      "tags": [
        "경향신문",
        "다음",
        "카카오 다음",
        "다음카카오",
        "카톡",
        "ict",
        "it",
        "모바일 라이프 플랫폼"
      ],
      "liveBroadcastContent": "none",
      "liveStreamingDetails": null,
      "actualPubAt": "2014-10-01T06:05:02Z",
      "channelId": "UCHXvjavEtkPFJCfGlm0wTXw",
      "channelName": "경향티비",
      "collectedAt": "2025-09-03T10:02:02Z"
    },
    "Uf98mkJt44w": {
      "videoId": "Uf98mkJt44w",
      "title": "국군의날, 사열하는 박근혜 대통령",
      "description": "기본이 튼튼한 국군! 미래를 준비하는 국군! 을  주제로 건군 제 66주년을 기념하는 국군의 날 행사가 1일 오전 충남 계룡대 연병장에서 개최됐다. 박근혜 대통령이 열병식을 하며 손을 들어 인사하고 있다. /신현종 기자\n\n\"병영문화 혁신 이뤄 軍, 환골탈태 해달라\"\n\nhttp://news.chosun.com/site/data/html_dir/2014/10/02/2014100200440.html",
      "publishedAt": "2014-10-01T14:53:33Z",
      "duration": "PT1M33S",
      "viewCount": 15185,
      "likeCount": 63,
      "commentCount": 7,
      "tags": [
        "국군의 날",
        "박근혜",
        "대통령",
        "육군",
        "공군",
        "계룡대",
        "해군",
        "신현종",
        "조선일보"
      ],
      "liveBroadcastContent": "none",
      "liveStreamingDetails": null,
      "actualPubAt": "2014-10-01T14:53:33Z",
      "channelId": "UCdp4_yTBhQmB8E339Lafzow",
      "channelName": "조선일보",
      "collectedAt": "2025-09-03T10:02:02Z"
    },
    "8jbFclT6WJ0": {
      "videoId": "8jbFclT6WJ0",
      "title": "3년 만에 만난 박원순시장과 나경원의원",
      "description": "새누리당 나경원 의원이 1일 박원순 서울시장의 서울시청사 집무실을 방문했다. 박 시장이 집무실 밖으로 나와 나 의원을 맞으며 악수하고 있다. 두 사람이 정식으로 만난 것은 지난 2011년 서울시장 보궐선거에서 맞붙었던 이후 처음이다. 이날 만남은 새누리당 서울시당위원장을 맡은 나 의원이 면담 신청을 해서 이뤄졌다./이태경 기자\n\n3년 만에 만난 박원순·나경원\n\nhttp://news.chosun.com/site/data/html_dir/2014/10/02/2014100200386.html",
      "publishedAt": "2014-10-01T13:55:09Z",
      "duration": "PT50S",
      "viewCount": 1490,
      "likeCount": 2,
      "commentCount": 0,
      "tags": [
        "박원순",
        "나경원",
        "박원순 시장",
        "서울시장",
        "나경원 의원",
        "박원순 나경원",
        "조선일보",
        "이태경 기자"
      ],
      "liveBroadcastContent": "none",
      "liveStreamingDetails": null,
      "actualPubAt": "2014-10-01T13:55:09Z",
      "channelId": "UCdp4_yTBhQmB8E339Lafzow",
      "channelName": "조선일보",
      "collectedAt": "2025-09-03T10:02:02Z"
    },
    "PXl0GRXjACc": {
      "videoId": "PXl0GRXjACc",
      "title": "(NAM) ‘체조요정 손연재’ 리듬체조 팀경기 아시안게임 최초 은메달",
      "description": "손연재가 ‘에이스’로 나선 한국 리듬체조 대표팀이 인천아시안게임 팀 경기에서 사상 첫 은메달을 따냈다. 12년만의 아시안게임 메달이자 최초의 은메달이다./남강호 기자\n\n[AG 체조] ‘강심장’ 손연재, 인천에서 더 강했다\n\nhttp://news.chosun.com/site/data/html_dir/2014/10/02/2014100200630.html",
      "publishedAt": "2014-10-01T13:31:22Z",
      "duration": "PT1M41S",
      "viewCount": 41369,
      "likeCount": 63,
      "commentCount": 2,
      "tags": [
        "손연재",
        "체조",
        "체조 요정",
        "손연재 은메달",
        "손연재 체조",
        "체조요정 손연재",
        "손연재 요정",
        "인천 아시안게임",
        "아시안게임",
        "아시안게임 체조",
        "아시안게임 손연재",
        "체조 은메달",
        "인천 아시안게임 체조",
        "조선일보",
        "남강호 기자",
        "Son Yeon-jae (Olympic Athlete)",
        "Asian Games (Recurring Event)",
        "Rhythmic Gymnastics (Sport)"
      ],
      "liveBroadcastContent": "none",
      "liveStreamingDetails": null,
      "actualPubAt": "2014-10-01T13:31:22Z",
      "channelId": "UCdp4_yTBhQmB8E339Lafzow",
      "channelName": "조선일보",
      "collectedAt": "2025-09-03T10:02:02Z"
    },
    "_BuPXSYg5GU": {
      "videoId": "_BuPXSYg5GU",
      "title": "현빈이 소개하는 K2 신제품 다운 재킷 '마조람 4'",
      "description": "배우 현빈이 2014년 10월 1일 오전 서울 성수동 K2 본사에서 열린 K2 신제품 다운 재킷 ‘마조람4’ 출시 기념 행사에 참석해 포토타임을 가지고 있다./김연정 기자",
      "publishedAt": "2014-10-01T12:37:37Z",
      "duration": "PT1M2S",
      "viewCount": 1523,
      "likeCount": 5,
      "commentCount": 0,
      "tags": [
        "현빈",
        "K2",
        "K2 재킷",
        "K2 다운 재킷",
        "K2 현빈",
        "현빈 재킷",
        "다운 재킷",
        "조선일보",
        "김연정 기자"
      ],
      "liveBroadcastContent": "none",
      "liveStreamingDetails": null,
      "actualPubAt": "2014-10-01T12:37:37Z",
      "channelId": "UCdp4_yTBhQmB8E339Lafzow",
      "channelName": "조선일보",
      "collectedAt": "2025-09-03T10:02:02Z"
    },
    "QtqDi4EtNXs": {
      "videoId": "QtqDi4EtNXs",
      "title": "국내 최초 원통형 탱크 없는'SM5 LPLi DONUT'",
      "description": "대한LPG협회와 르노삼성자동차가 1일 국내 최초로 도넛 모양의 납작한 LPG 탱크를 개발해 탑재한 SM5 LPLi 도넛 모델을 선보였다. 르노삼성자동차는 기존 원통형 연료탱크 대신 납작한 도넛 모양의 탱크를 적용해 트렁크 공간을 기존 LPG 차량보다 40% 늘렸다고 밝혔다./김연정 기자",
      "publishedAt": "2014-10-01T12:09:37Z",
      "duration": "PT50S",
      "viewCount": 1811,
      "likeCount": 0,
      "commentCount": 0,
      "tags": [
        "sm5",
        "탱크",
        "lpg",
        "탱크 없는 자통차",
        "연료탱크",
        "도넛모양 탱크",
        "도넛 탱크",
        "LPG탱크",
        "르노삼성자동차",
        "르노",
        "르노 삼성",
        "삼성",
        "조선일보",
        "김연정 기자"
      ],
      "liveBroadcastContent": "none",
      "liveStreamingDetails": null,
      "actualPubAt": "2014-10-01T12:09:37Z",
      "channelId": "UCdp4_yTBhQmB8E339Lafzow",
      "channelName": "조선일보",
      "collectedAt": "2025-09-03T10:02:02Z"
    },
    "9HqxeF70Xyg": {
      "videoId": "9HqxeF70Xyg",
      "title": "영화 '슬로우 비디오'의 ‘여장부’ 역 차태현",
      "description": "아이 셋을 둔 아버지임에도 차태현은 여전히 동네 형 같은 인상을 갖고 있다. 그는 20대 초반에 동안(童顔)이란 이유로 드라마에서 하차까지 한 적도 있지만, 지금은 오히려 “아이 셋 둔 아빠 느낌이 별로 안 나서” 다행이란다./김지호 기자\n\n어떤 役이든 '차태현化'해드립니다\n\nhttp://news.chosun.com/site/data/html_dir/2014/10/02/2014100200167.html",
      "publishedAt": "2014-10-01T12:08:44Z",
      "duration": "PT1M36S",
      "viewCount": 2276,
      "likeCount": 16,
      "commentCount": 1,
      "tags": [
        "차태현",
        "슬로우 비디오",
        "영화 슬로우 비디오",
        "차태현 영화",
        "슬로우 비디오 차태현",
        "차태현 연기",
        "조선일보",
        "김지호 기자"
      ],
      "liveBroadcastContent": "none",
      "liveStreamingDetails": null,
      "actualPubAt": "2014-10-01T12:08:44Z",
      "channelId": "UCdp4_yTBhQmB8E339Lafzow",
      "channelName": "조선일보",
      "collectedAt": "2025-09-03T10:02:02Z"
    },
    "ov8mUcp3yIg": {
      "videoId": "ov8mUcp3yIg",
      "title": "SNL 코리아 극한직업의 ‘유병재’",
      "description": "유병재는 좀 더 웃긴 외모를 만들려고 일부러 수염을 길렀다. 그는 “명절 때 조카들이 날 보면 항상 울거나 구토를 하는데 왜 그러는지 모르겠다”고 말했다./이태경 기자\n\n울어도 웃긴 이 男子, 매력은 서러움\n\nhttp://news.chosun.com/site/data/html_dir/2014/10/02/2014100200181.html",
      "publishedAt": "2014-10-01T12:03:40Z",
      "duration": "PT1M14S",
      "viewCount": 16935,
      "likeCount": 25,
      "commentCount": 2,
      "tags": [
        "유병재",
        "SNL",
        "SNL 유병재",
        "SNL 극한직업",
        "극한직업",
        "극한직업 유병재",
        "극한직업 신해철",
        "유병재 신해철",
        "유병재 작가",
        "SNL 작가",
        "조선일보",
        "이태경 기자"
      ],
      "liveBroadcastContent": "none",
      "liveStreamingDetails": null,
      "actualPubAt": "2014-10-01T12:03:40Z",
      "channelId": "UCdp4_yTBhQmB8E339Lafzow",
      "channelName": "조선일보",
      "collectedAt": "2025-09-03T10:02:02Z"
    },
    "oBtBNNHeZsE": {
      "videoId": "oBtBNNHeZsE",
      "title": "다음과 카카오의 합병법인 ‘다음카카오’ 공식 출범",
      "description": "국내 최대 모바일 메신저 ‘카카오톡’을 운영하는 ㈜카카오가 국내 2위 포털 다음커뮤니케이션(이하 다음)과 1일 공식 합병, ‘다음카카오’로 재탄생했다./김연정 기자\n\n다음카카오 출범, 최세훈-이석우 공동대표 체재…\"새로운 세상 만들겠다\"\n\nhttp://news.chosun.com/site/data/html_dir/2014/10/01/2014100105192.html",
      "publishedAt": "2014-10-01T11:59:52Z",
      "duration": "PT1M20S",
      "viewCount": 251,
      "likeCount": 1,
      "commentCount": 0,
      "tags": [
        "카카오",
        "카카오 톡",
        "다음",
        "다음카카오",
        "다음 카카오",
        "카카오 합병",
        "카카오톡 합병",
        "다음 합병",
        "카카오톡 다음 합병",
        "카카오 다음 합병",
        "조선일보",
        "김연정 기자"
      ],
      "liveBroadcastContent": "none",
      "liveStreamingDetails": null,
      "actualPubAt": "2014-10-01T11:59:52Z",
      "channelId": "UCdp4_yTBhQmB8E339Lafzow",
      "channelName": "조선일보",
      "collectedAt": "2025-09-03T10:02:02Z"
    },
    "9vaBFZmQQEc": {
      "videoId": "9vaBFZmQQEc",
      "title": "연극 '고곤의 선물'의 천재 극작가역 박상원",
      "description": "연극 ‘고곤의 선물’에 더블캐스트로 출연 중인 박상원은 “주인공을 가슴이 뜨거운 극단주의자로 해석했다”고 말했다./김연정 기자\n\n돌아온 것 아냐, 원래 제 자린걸요\n\nhttp://news.chosun.com/site/data/html_dir/2014/10/02/2014100200165.html",
      "publishedAt": "2014-10-01T11:49:05Z",
      "duration": "PT37S",
      "viewCount": 520,
      "likeCount": 1,
      "commentCount": 0,
      "tags": [
        "박상원",
        "고곤의 선물",
        "연극",
        "연극 고곤의 선물",
        "연극 고곤",
        "연극 박상원",
        "박상원 연극",
        "극단",
        "더블 캐스트",
        "더블 캐스팅",
        "캐스팅",
        "박상원 연기",
        "조선일보",
        "김연정 기자"
      ],
      "liveBroadcastContent": "none",
      "liveStreamingDetails": null,
      "actualPubAt": "2014-10-01T11:49:05Z",
      "channelId": "UCdp4_yTBhQmB8E339Lafzow",
      "channelName": "조선일보",
      "collectedAt": "2025-09-03T10:02:02Z"
    },
    "rZrvUAyxGFI": {
      "videoId": "rZrvUAyxGFI",
      "title": "2014 세계불꽃축제, 여의도",
      "description": "10월 1일 오전 서울 선유도 공원 선착장에서 불꽃놀이 장인들이 오는 4일 여의도 한강시민공원에서 열리는 '2014 서울세계불꽃축제'를 준비하고 있다.",
      "publishedAt": "2014-10-01T09:57:26Z",
      "duration": "PT1M5S",
      "viewCount": 774,
      "likeCount": 0,
      "commentCount": 0,
      "tags": [
        "불꽃축제",
        "불꽃",
        "여의도",
        "시민공원",
        "세계불꽃축제",
        "윤동진"
      ],
      "liveBroadcastContent": "none",
      "liveStreamingDetails": null,
      "actualPubAt": "2014-10-01T09:57:26Z",
      "channelId": "UCdp4_yTBhQmB8E339Lafzow",
      "channelName": "조선일보",
      "collectedAt": "2025-09-03T10:02:02Z"
    },
    "YHPC6DqHW2I": {
      "videoId": "YHPC6DqHW2I",
      "title": "여군들의 특공무술",
      "description": "30일 충남 계룡시 계룡대 대연병장에서 열린 ‘건군 제66주년 국군의 날’ 행사 최종 리허설에서 특공무술 시범에 나선 여군들이 적들의 간담을 서늘하게 할 특공무술을 선보였다. /신현종 기자",
      "publishedAt": "2014-09-30T16:33:09Z",
      "duration": "PT1M28S",
      "viewCount": 388405,
      "likeCount": 611,
      "commentCount": 137,
      "tags": [
        "여군",
        "여군특공무술",
        "특공무술",
        "특전사대원",
        "특전사",
        "계룡대",
        "국군의날",
        "신현종",
        "조선일보"
      ],
      "liveBroadcastContent": "none",
      "liveStreamingDetails": null,
      "actualPubAt": "2014-09-30T16:33:09Z",
      "channelId": "UCdp4_yTBhQmB8E339Lafzow",
      "channelName": "조선일보",
      "collectedAt": "2025-09-03T10:02:02Z"
    },
    "49E8498BTps": {
      "videoId": "49E8498BTps",
      "title": "한국타이어 대전공장 큰 불…인근 아파트 주민 대피",
      "description": "한국타이어 대전공장 물류창고에서 화재가 발생해 소방당국이 진화 작업을 벌이고 있다. 30일 오후 8시 55분쯤 대전 대덕구 목상동에 있는 한국타이어 대전공장 물류창고에서 화재가 발생했다. 화재가 발생했을 당시 대전공장에서 일하고 있던 작업자 1000여명은 긴급 대피했다. 인근 아파트 주민들은 연기로 인해 긴급대피한 상태다. /신현종 기자\n\n한국타이어 대전공장 화재…총 66억원 재산 피해 입어 ‘인명 피해 없다’\n\nhttp://news.chosun.com/site/data/html_dir/2014/10/01/2014100101282.html",
      "publishedAt": "2014-09-30T15:29:26Z",
      "duration": "PT1M19S",
      "viewCount": 7572,
      "likeCount": 8,
      "commentCount": 3,
      "tags": [
        "한국타이어",
        "한국타이어 화재",
        "한국타이어 큰불",
        "한국타이어 대전공장",
        "신현종",
        "조선일보"
      ],
      "liveBroadcastContent": "none",
      "liveStreamingDetails": null,
      "actualPubAt": "2014-09-30T15:29:26Z",
      "channelId": "UCdp4_yTBhQmB8E339Lafzow",
      "channelName": "조선일보",
      "collectedAt": "2025-09-03T10:02:02Z"
    },
    "kiXZTm55GYg": {
      "videoId": "kiXZTm55GYg",
      "title": "930‘세월호법 합의안’…가이드라인에 갇혔다",
      "description": "2014년 9월 30일 국회 운영위원회\n \n‘세월호 특별법’에 양당이 합의사항을김재원 새누리당 원내수석부대표가 공개했다. 여야 원대 대표단이 취재진 앞에 모습을 드러냈다. “악수 한번 하십시오”  이완구 새누리당 원내대표 “우선 읽고 난 다음에 합시다” 누구는 환하게 웃으며 누구는 굳은 표정으로 손을 잡았다.  기자들은 질문했다. “유가족 쪽에서 반대한다는...” 김재원 새누리당 원내수석부대표 “질문은 하지 않기로 했습니다.”  “2번 조항은 좀 애매하다는 이야기가 나오는데요.” “정치적 중립성을 보장할 수 없는 후보가 어떤 겁니까?” 유가족대책위는 여야 합의안을 받아 드릴 수 없다고 밝혔다.\n  \n세월호 참사 168째 그동안 시신 294구가 수습되었고 학생 5명, 교사2명, 일반인3명이 아직도 진도 앞바다에 있다.",
      "publishedAt": "2014-10-01T01:20:37Z",
      "duration": "PT3M5S",
      "viewCount": 7932,
      "likeCount": 11,
      "commentCount": 0,
      "tags": [
        "세월호법",
        "이완구",
        "박영선",
        "합의안",
        "930"
      ],
      "liveBroadcastContent": "none",
      "liveStreamingDetails": null,
      "actualPubAt": "2014-10-01T01:20:37Z",
      "channelId": "UCugbqfMO94F9guLEb6Olb2A",
      "channelName": "한겨레TV",
      "collectedAt": "2025-09-03T10:47:53Z"
    },
    "-sPb5kcRbMU": {
      "videoId": "-sPb5kcRbMU",
      "title": "930  ‘세월호법 합의안’...가이드라인에 갇혔다",
      "description": "2014년 9월 30일 국회 운영위원회\r\n\r\n‘세월호 특별법’에 양당이 합의사항을김재원 새누리당 원내수석부대표가 공개했다. \r\n\r\n여야 원대 대표단이 취재진 앞에 모습을 드러냈다.\r\n\r\n“악수 한번 하십시오”\r\n\r\n이완구 새누리당 원내대표\r\n“우선 읽고 난 다음에 합시다”\r\n\r\n누구는 환하게 웃으며 누구는 굳은 표정으로 손을 잡았다.\r\n\r\n기자들은 질문했다.\r\n\r\n“유가족 쪽에서 반대한다는...”\r\n\r\n김재원 새누리당 원내수석부대표\r\n“질문은 하지 않기로 했습니다.”\r\n\r\n“2번 조항은 좀 애매하다는 이야기가 나오는데요.”\r\n\r\n“정치적 중립성을 보장할 수 없는 후보가 어떤 겁니까?”\r\n\r\n유가족대책위는 여야 합의안을 받아 드릴 수 없다고 밝혔다.\r\n\r\n\r\n\r\n세월호 참사 168째\r\n그동안 시신 294구가 수습되었고 \r\n학생 5명, 교사2명, 일반인3명이 \r\n아직도 진도 앞바다에 있다.",
      "publishedAt": "2014-09-30T15:25:43Z",
      "duration": "PT2M18S",
      "viewCount": 2060,
      "likeCount": 4,
      "commentCount": 0,
      "tags": [],
      "liveBroadcastContent": "none",
      "liveStreamingDetails": null,
      "actualPubAt": "2014-09-30T15:25:43Z",
      "channelId": "UCugbqfMO94F9guLEb6Olb2A",
      "channelName": "한겨레TV",
      "collectedAt": "2025-09-03T10:47:53Z"
    }
  },
  "channels": {
    "UCWlV3Lz_55UaX4JsMj-z__Q": {
      "channelId": "UCWlV3Lz_55UaX4JsMj-z__Q",
      "channelName": "뉴스TVCHOSUN",
      "channelUrl": "@tvchosunnews",
      "channelDescription": "TV조선 뉴스 공식 YouTube 입니다.",
      "channelThumbnails": {
        "default": {
          "url": "https://yt3.ggpht.com/AtOfk6Ivk4KYoHNxFu4VOUez9H8d5uN4tNWO95wruz1_cfXWKn_FuEHmXjOl7kaE9MUzieaDuw=s88-c-k-c0x00ffffff-no-rj",
          "width": 88,
          "height": 88
        },
        "medium": {
          "url": "https://yt3.ggpht.com/AtOfk6Ivk4KYoHNxFu4VOUez9H8d5uN4tNWO95wruz1_cfXWKn_FuEHmXjOl7kaE9MUzieaDuw=s240-c-k-c0x00ffffff-no-rj",
          "width": 240,
          "height": 240
        },
        "high": {
          "url": "https://yt3.ggpht.com/AtOfk6Ivk4KYoHNxFu4VOUez9H8d5uN4tNWO95wruz1_cfXWKn_FuEHmXjOl7kaE9MUzieaDuw=s800-c-k-c0x00ffffff-no-rj",
          "width": 800,
          "height": 800
        }
      },
      "subscriberCount": 2900000,
      "viewCount": 4319423561,
      "videoCount": 150855,
      "lastUpdated": "2025-08-21T10:28:55.317665Z"
    },
    "UC4Aa3OPkMenwTANpf0oWVRQ": {
      "channelId": "UC4Aa3OPkMenwTANpf0oWVRQ",
      "channelName": "CBS 김현정의 뉴스쇼",
      "channelUrl": "@cbsnewsshow",
      "channelDescription": "김현정의 뉴스쇼는 정치 사회의 주요 인사는 물론, 화제의 인물을 실시간으로 연결합니다\n\n여러분의 소중한 제보를 받습니다\n잘 알려지지 않았지만 꼭 다뤄져야 할 중요한 사안이 있을 경우\n메일, 문자 또는 레인보우 게시판을 통해 제보해 주세요\n \n프로그램 아이템으로 적합한 경우, 검토 이후 방송에 반영하겠습니다\n\n\n\n▣ 제보 및 의견\n◇ 문자: #1212\n◇ 뉴스쇼 제보 이메일: cbsnewsshow@gmail.com\n◇ 댓꿀쇼 관련 이메일: newsshow.cbs@gmail.com\n\n▣ 방송 안내\n뉴스쇼 채널 | CBS FM 98.1\n뉴스쇼 라이브 방송 | 매주 월~금 오전 7:10~9:00\n댓꿀쇼 라이브 방송 | 화·목·금 주 3회, 본방송 이후 9시",
      "channelThumbnails": {
        "default": {
          "url": "https://yt3.ggpht.com/KYgdx4DjWKWPBr36jSzzGd5wrgw5ffMBVqHUJanuLKWeidLoeLaETpx29lPEx9c-Z3eMe-tsrSU=s88-c-k-c0x00ffffff-no-rj",
          "width": 88,
          "height": 88
        },
        "medium": {
          "url": "https://yt3.ggpht.com/KYgdx4DjWKWPBr36jSzzGd5wrgw5ffMBVqHUJanuLKWeidLoeLaETpx29lPEx9c-Z3eMe-tsrSU=s240-c-k-c0x00ffffff-no-rj",
          "width": 240,
          "height": 240
        },
        "high": {
          "url": "https://yt3.ggpht.com/KYgdx4DjWKWPBr36jSzzGd5wrgw5ffMBVqHUJanuLKWeidLoeLaETpx29lPEx9c-Z3eMe-tsrSU=s800-c-k-c0x00ffffff-no-rj",
          "width": 800,
          "height": 800
        }
      },
      "subscriberCount": 1590000,
      "viewCount": 1280577570,
      "videoCount": 19124,
      "lastUpdated": "2025-08-24T21:55:01.038113Z"
    },
    "UCsU-I-vHLiaMfV_ceaYz5rQ": {
      "channelId": "UCsU-I-vHLiaMfV_ceaYz5rQ",
      "channelName": "JTBC News",
      "channelUrl": "@jtbc_news",
      "channelDescription": "진실에 닿을 때까지 멈추지 않는 질문, JTBC News\nWelcome to the official JTBC News Channel.\n\n▶ https://news.jtbc.co.kr\n",
      "channelThumbnails": {
        "default": {
          "url": "https://yt3.ggpht.com/huo8anjEzTu67FuF6mO6ui8beFyZ2rECX6-WkshXZlEfohUB1R8o66jGRbhAErooLYAXxH9U27E=s88-c-k-c0x00ffffff-no-rj",
          "width": 88,
          "height": 88
        },
        "medium": {
          "url": "https://yt3.ggpht.com/huo8anjEzTu67FuF6mO6ui8beFyZ2rECX6-WkshXZlEfohUB1R8o66jGRbhAErooLYAXxH9U27E=s240-c-k-c0x00ffffff-no-rj",
          "width": 240,
          "height": 240
        },
        "high": {
          "url": "https://yt3.ggpht.com/huo8anjEzTu67FuF6mO6ui8beFyZ2rECX6-WkshXZlEfohUB1R8o66jGRbhAErooLYAXxH9U27E=s800-c-k-c0x00ffffff-no-rj",
          "width": 800,
          "height": 800
        }
      },
      "subscriberCount": 4670000,
      "viewCount": 14817048106,
      "videoCount": 261473,
      "lastUpdated": "2025-08-25T21:08:23.334003Z"
    },
    "UCfq4V1DAuaojnr2ryvWNysw": {
      "channelId": "UCfq4V1DAuaojnr2ryvWNysw",
      "channelName": "채널A News",
      "channelUrl": "@channela-news",
      "channelDescription": "당신의 목소리, 채널A News",
      "channelThumbnails": {
        "default": {
          "url": "https://yt3.ggpht.com/Pjh8brk90jdspfc5dKpfxq7DliuPRH3j5UIlX13b5HGe4eK0_PSFLqRdySsHYA_McUwKM2F_8g=s88-c-k-c0x00ffffff-no-rj",
          "width": 88,
          "height": 88
        },
        "medium": {
          "url": "https://yt3.ggpht.com/Pjh8brk90jdspfc5dKpfxq7DliuPRH3j5UIlX13b5HGe4eK0_PSFLqRdySsHYA_McUwKM2F_8g=s240-c-k-c0x00ffffff-no-rj",
          "width": 240,
          "height": 240
        },
        "high": {
          "url": "https://yt3.ggpht.com/Pjh8brk90jdspfc5dKpfxq7DliuPRH3j5UIlX13b5HGe4eK0_PSFLqRdySsHYA_McUwKM2F_8g=s800-c-k-c0x00ffffff-no-rj",
          "width": 800,
          "height": 800
        }
      },
      "subscriberCount": 3260000,
      "viewCount": 6198116921,
      "videoCount": 143713,
      "lastUpdated": "2025-08-26T12:50:28.881519Z"
    },
    "UChlgI3UHCOnwUGzWzbJ3H5w": {
      "channelId": "UChlgI3UHCOnwUGzWzbJ3H5w",
      "channelName": " YTN",
      "channelUrl": "@ytnnews24",
      "channelDescription": "24시간 생중계되는 대한민국 대표 뉴스\nYTN 공식채널을 지금 바로 구독하세요\n\n▶ 구독하기 : http://goo.gl/Ytb5SZ\n\n▶ YTN 기사제보 안내\n- 홈페이지: https://mj.ytn.co.kr/mj/mj_write.php?sort=0\n- 모바일: YTN 앱의 제보하기\n- 이메일: social@ytn.co.kr\n- 전화: 02-398-8282 또는 8585 \n\n▶ 라이브 스트리밍 대체광고 및 콘텐츠 협업 문의\n - 이메일 : ljk@ytn.co.kr\n\n▶ 영상 사용 및 구매 문의\n - https://www.ytn.co.kr/business/sell_program.php\n",
      "channelThumbnails": {
        "default": {
          "url": "https://yt3.ggpht.com/Sd77hfGXNh1K4VgLCnYVrzWVkUKh04N5VDClPweoP-sbaZXzH3llUz2W1N_-Z4RX5_XauYpvSQ=s88-c-k-c0x00ffffff-no-rj",
          "width": 88,
          "height": 88
        },
        "medium": {
          "url": "https://yt3.ggpht.com/Sd77hfGXNh1K4VgLCnYVrzWVkUKh04N5VDClPweoP-sbaZXzH3llUz2W1N_-Z4RX5_XauYpvSQ=s240-c-k-c0x00ffffff-no-rj",
          "width": 240,
          "height": 240
        },
        "high": {
          "url": "https://yt3.ggpht.com/Sd77hfGXNh1K4VgLCnYVrzWVkUKh04N5VDClPweoP-sbaZXzH3llUz2W1N_-Z4RX5_XauYpvSQ=s800-c-k-c0x00ffffff-no-rj",
          "width": 800,
          "height": 800
        }
      },
      "subscriberCount": 5150000,
      "viewCount": 17649222300,
      "videoCount": 890317,
      "lastUpdated": "2025-08-29T02:42:34.157295Z"
    },
    "UC1aS5CRRDrN6CmR2VcpmetA": {
      "channelId": "UC1aS5CRRDrN6CmR2VcpmetA",
      "channelName": "한국일보(hankookilbo.com)",
      "channelUrl": "@thehankookilbo",
      "channelDescription": "'공존, 통합, 사람'의 정신으로 앞장서는 국내 유일 중도 정론지 한국일보입니다.\n",
      "channelThumbnails": {
        "default": {
          "url": "https://yt3.ggpht.com/ppj3UlPuwNq5DyUWNFz27Vc6WoIrRpRI2IMHc9MZ3UqkNVWcXrT83qJTU3bAweA3BOodFu4Euf0=s88-c-k-c0x00ffffff-no-rj",
          "width": 88,
          "height": 88
        },
        "medium": {
          "url": "https://yt3.ggpht.com/ppj3UlPuwNq5DyUWNFz27Vc6WoIrRpRI2IMHc9MZ3UqkNVWcXrT83qJTU3bAweA3BOodFu4Euf0=s240-c-k-c0x00ffffff-no-rj",
          "width": 240,
          "height": 240
        },
        "high": {
          "url": "https://yt3.ggpht.com/ppj3UlPuwNq5DyUWNFz27Vc6WoIrRpRI2IMHc9MZ3UqkNVWcXrT83qJTU3bAweA3BOodFu4Euf0=s800-c-k-c0x00ffffff-no-rj",
          "width": 800,
          "height": 800
        }
      },
      "subscriberCount": 362000,
      "viewCount": 296027619,
      "videoCount": 6197,
      "lastUpdated": "2025-09-03T10:17:10.411178Z"
    },
    "UCHXvjavEtkPFJCfGlm0wTXw": {
      "channelId": "UCHXvjavEtkPFJCfGlm0wTXw",
      "channelName": "경향티비",
      "channelUrl": "@thekyunghyangtv",
      "channelDescription": "더 나은 세상을 위해 우리가 알아야 할 이야기\n경향신문 공식 채널\n\n🚨 [정치비상구] 출구없는 극단 정치, 비상구를 열어드립니다\n🎙️ 매주 월-금 오후 4시 라이브 ｜ 토요특별판 낮 12시\n🎙️ 정치인물사담회 '인물비상구' 일요일 오후 4시\n 📞광고/제휴 문의 : insaps10@gmail.com\n",
      "channelThumbnails": {
        "default": {
          "url": "https://yt3.ggpht.com/6Wlbqcuxx1ESFI2U-gQqhHyYpJ-PiWgqyjotWwD9VN5JygRnIuUvZE1LjUMwKNbb5LqRCEM4kpQ=s88-c-k-c0x00ffffff-no-rj",
          "width": 88,
          "height": 88
        },
        "medium": {
          "url": "https://yt3.ggpht.com/6Wlbqcuxx1ESFI2U-gQqhHyYpJ-PiWgqyjotWwD9VN5JygRnIuUvZE1LjUMwKNbb5LqRCEM4kpQ=s240-c-k-c0x00ffffff-no-rj",
          "width": 240,
          "height": 240
        },
        "high": {
          "url": "https://yt3.ggpht.com/6Wlbqcuxx1ESFI2U-gQqhHyYpJ-PiWgqyjotWwD9VN5JygRnIuUvZE1LjUMwKNbb5LqRCEM4kpQ=s800-c-k-c0x00ffffff-no-rj",
          "width": 800,
          "height": 800
        }
      },
      "subscriberCount": 537000,
      "viewCount": 354014202,
      "videoCount": 11631,
      "lastUpdated": "2025-09-03T10:17:10.411178Z"
    },
    "UCdp4_yTBhQmB8E339Lafzow": {
      "channelId": "UCdp4_yTBhQmB8E339Lafzow",
      "channelName": "조선일보",
      "channelUrl": "@chosunmedia",
      "channelDescription": " 조선일보 공식 유튜브 채널",
      "channelThumbnails": {
        "default": {
          "url": "https://yt3.ggpht.com/GsFAtvQbKEaB_dq0WVJWl3y67XdR_EC4mTaBUwsY0xaL0jorggzMAyi8q2BXIrgy57Pu5hlJ=s88-c-k-c0x00ffffff-no-rj",
          "width": 88,
          "height": 88
        },
        "medium": {
          "url": "https://yt3.ggpht.com/GsFAtvQbKEaB_dq0WVJWl3y67XdR_EC4mTaBUwsY0xaL0jorggzMAyi8q2BXIrgy57Pu5hlJ=s240-c-k-c0x00ffffff-no-rj",
          "width": 240,
          "height": 240
        },
        "high": {
          "url": "https://yt3.ggpht.com/GsFAtvQbKEaB_dq0WVJWl3y67XdR_EC4mTaBUwsY0xaL0jorggzMAyi8q2BXIrgy57Pu5hlJ=s800-c-k-c0x00ffffff-no-rj",
          "width": 800,
          "height": 800
        }
      },
      "subscriberCount": 1700000,
      "viewCount": 1669752256,
      "videoCount": 22784,
      "lastUpdated": "2025-09-03T10:17:10.411178Z"
    },
    "UCugbqfMO94F9guLEb6Olb2A": {
      "channelId": "UCugbqfMO94F9guLEb6Olb2A",
      "channelName": "한겨레TV",
      "channelUrl": "@hankyorehtv",
      "channelDescription": "'더불어 행복한 세상을 만드는 언론' 한겨레 공식 유튜브 채널입니다. \n ■ 편성 및 제휴 문의: leepd@hani.co.kr\n",
      "channelThumbnails": {
        "default": {
          "url": "https://yt3.ggpht.com/lrhT-9GirTu8tJAHggeD49Qv7mgMwy0yljNYixQMbP6N9xi7tTwq3U6TsTolyPm-wHkf6UpECAo=s88-c-k-c0x00ffffff-no-rj",
          "width": 88,
          "height": 88
        },
        "medium": {
          "url": "https://yt3.ggpht.com/lrhT-9GirTu8tJAHggeD49Qv7mgMwy0yljNYixQMbP6N9xi7tTwq3U6TsTolyPm-wHkf6UpECAo=s240-c-k-c0x00ffffff-no-rj",
          "width": 240,
          "height": 240
        },
        "high": {
          "url": "https://yt3.ggpht.com/lrhT-9GirTu8tJAHggeD49Qv7mgMwy0yljNYixQMbP6N9xi7tTwq3U6TsTolyPm-wHkf6UpECAo=s800-c-k-c0x00ffffff-no-rj",
          "width": 800,
          "height": 800
        }
      },
      "subscriberCount": 946000,
      "viewCount": 586539536,
      "videoCount": 9682,
      "lastUpdated": "2025-09-03T10:47:53.803005Z"
    }
  },
  "lastUpdated": "2025-09-03T10:47:53.803005Z",
  "totalVideos": 51,
  "totalChannels": 9
}