{
  "videos": {
    "tuUtI3Gks1E": {
      "videoId": "tuUtI3Gks1E",
      "title": "평창 동계올림픽, 성공으로 가는 길 - NATV 직언직설 토론당당",
      "description": "2018/02/07 직언직설 토론당당  22회\n\n평창 동계올림픽, 성공으로 가는 길\n\n출연자\n심 기 준 (더불어민주당 / 국회 평창특위 위원)\n염 동 열 (자유한국당 / 국회 평창특위 간사)",
      "publishedAt": "2018-02-08T03:33:47Z",
      "duration": "PT50M52S",
      "viewCount": 182,
      "likeCount": 1,
      "commentCount": 0,
      "tags": [
        "평창동계올림픽",
        "평창올림픽",
        "평양올림픽",
        "평창특위",
        "평창특별위원회",
        "남북단일팀",
        "한반도기",
        "남북공동입장",
        "여자아이스하키",
        "아이스하키단일팀"
      ],
      "categoryId": "29",
      "defaultLanguage": null,
      "defaultAudioLanguage": null,
      "liveBroadcastContent": "none",
      "liveStreamingDetails": null,
      "channelId": "UCL-WOj1FxKR8Hlzg5tvnWKg",
      "channelName": "NATV 국회방송",
      "collectedAt": "2025-08-20T11:40:00.428178Z"
    },
    "cCX-eiaydog": {
      "videoId": "cCX-eiaydog",
      "title": "2018  평창 동계올림픽 최종주자는 김연아선수 - 김연아 명장면 다시보기",
      "description": "평창동계올림픽을 하루 앞두고 김연아 선수의 감동적이었던 경기를 모아봤는데요!\n사실상 그녀의 은퇴무대였던 소치올림픽의 쇼트, 프리, 갈라 세 경기를 감상하시죠",
      "publishedAt": "2018-02-08T08:38:36Z",
      "duration": "PT2M4S",
      "viewCount": 6691,
      "likeCount": 43,
      "commentCount": 1,
      "tags": [
        "KTV 국민방송",
        "한국정책방송 KTV",
        "김연아",
        "김연아 갈라쇼",
        "김연아 레전드",
        "김연아 명장면",
        "소치올림픽",
        "피겨스케이팅",
        "아디오스 노니노",
        "어릿광대를 보내주오"
      ],
      "categoryId": "25",
      "defaultLanguage": "ko",
      "defaultAudioLanguage": "ko",
      "liveBroadcastContent": "none",
      "liveStreamingDetails": null,
      "channelId": "UCIMOytYIzaUpoAM2bpT4JZQ",
      "channelName": "KTV 국민방송",
      "collectedAt": "2025-08-20T11:40:00.429175Z"
    },
    "EW7BJEPX0pU": {
      "videoId": "EW7BJEPX0pU",
      "title": "김정숙 여사 “여러분도 평창올림픽의 또하나의 선수입니다” 자원봉사자 격려",
      "description": "김정숙 여사가 7일 강원 평창 올림픽 선수촌을 방문, 자원봉사자들을 격려하였습니다. 김정숙 여사는 “여러분들은 평창올림픽의 또 하나의 종목에 출전하는 선수들입니다.” 라 전하며 평창올림픽 현장 곳곳의 자원봉사자들을 만나 격려와 감사의 인사를 전했습니다.",
      "publishedAt": "2018-02-08T08:17:19Z",
      "duration": "PT1M57S",
      "viewCount": 13188,
      "likeCount": 374,
      "commentCount": 89,
      "tags": [
        "KTV 국민방송",
        "한국정책방송 KTV",
        "김정숙",
        "여사",
        "평창",
        "동계",
        "올림픽",
        "평창동계올림픽",
        "선수촌",
        "자원봉사자"
      ],
      "categoryId": "25",
      "defaultLanguage": null,
      "defaultAudioLanguage": "ko",
      "liveBroadcastContent": "none",
      "liveStreamingDetails": null,
      "channelId": "UCIMOytYIzaUpoAM2bpT4JZQ",
      "channelName": "KTV 국민방송",
      "collectedAt": "2025-08-20T11:40:00.429175Z"
    },
    "gy6sDu9SOBM": {
      "videoId": "gy6sDu9SOBM",
      "title": "홍종학 장관 ”사업자 부담 덜고 임금 보장” 일자리 안정자금 신청하세요",
      "description": "홍종학 중소벤처기업부 장관은 2018년 최저임금을 보장하는 모범기업을 방문하여 격려하고 일자리 안정자금 신청을 안내하는 릴레이식 \"일자리 안정자금 현장홍보\"를 이어갔습니다.",
      "publishedAt": "2018-02-08T05:12:07Z",
      "duration": "PT58S",
      "viewCount": 176,
      "likeCount": 20,
      "commentCount": 1,
      "tags": [
        "KTV 국민방송",
        "한국정책방송 KTV",
        "일",
        "일자리",
        "취업",
        "취준생",
        "홍종학",
        "중소벤처기업부",
        "장관",
        "최저임금"
      ],
      "categoryId": "25",
      "defaultLanguage": null,
      "defaultAudioLanguage": "ko",
      "liveBroadcastContent": "none",
      "liveStreamingDetails": null,
      "channelId": "UCIMOytYIzaUpoAM2bpT4JZQ",
      "channelName": "KTV 국민방송",
      "collectedAt": "2025-08-20T11:40:00.429175Z"
    },
    "Zr-TR85m0IE": {
      "videoId": "Zr-TR85m0IE",
      "title": "평창 계기 정상외교 돌입, 펜스ㆍ아베ㆍ김영남 방한 의미는?",
      "description": "🎥[Live] 평창 계기 정상외교 돌입, 펜스ㆍ아베ㆍ김영남 방한의미는?\n\n✔김여정 제1부부장 방남, 남북·북미대화 가능성은?\n✔평창올림픽 기간 외교전, 의미는?\n✔펜스 부통령, 북한에 강경한 메시지 남길 목적\n✔남북관계 개선, 북미대화로 확장 가능성은?",
      "publishedAt": "2018-02-08T02:11:04Z",
      "duration": "PT21M",
      "viewCount": 289,
      "likeCount": 10,
      "commentCount": 0,
      "tags": [
        "김여정",
        "김영남",
        "펜스",
        "아베",
        "문재인",
        "평창"
      ],
      "categoryId": "25",
      "defaultLanguage": null,
      "defaultAudioLanguage": null,
      "liveBroadcastContent": "none",
      "liveStreamingDetails": {
        "actualStartTime": "2018-02-08T01:14:29Z",
        "actualEndTime": "2018-02-08T01:37:17Z"
      },
      "channelId": "UCIMOytYIzaUpoAM2bpT4JZQ",
      "channelName": "KTV 국민방송",
      "collectedAt": "2025-08-20T11:40:00.429175Z"
    },
    "Jye1KU_6pVY": {
      "videoId": "Jye1KU_6pVY",
      "title": "문 대통령·펜스 “최대 압박 통한 北비핵화 대화 원칙 확인” - 문재인 대통령, 펜스 美 부통령 접견 및 만찬 청와대 브리핑",
      "description": "🎥[Live] 문 대통령·펜스 “최대 압박 통한 北비핵화 대화 원칙 확인”\n- 문재인 대통령, 펜스 美 부통령 접견 및 만찬 청와대 브리핑\n\n✔문재인 대통령이 미국 펜스 부통령을 접견하고 한미 공조 방안을 논의했습니다.\n\n✔문 대통령과 펜스 부통령은 그간 누차 밝혔듯이 최대한의 제재와 압박을 통해 북한을 비핵화를 위한 대화로 이끌어낸다는 원칙을 재확인하고 필요한 협력을 계속해 나가기로 했습니다.\n\n✔펜스 부통령은 트럼프 대통령의 문 대통령에 대한 각별한 안부와 동맹으로서 평창 동계올림픽의 안전하고 성공적인 개최를 전폭적으로 지지한다는 메시지를 전하는 한편 한국에 대한 철통 같은 방위 공약을 재확인하면서 한미 동맹이 어느 때보다도 강력하다는 문 대통령의 평가에 공감을 표시했습니다.",
      "publishedAt": "2018-02-08T13:18:01Z",
      "duration": "PT2M57S",
      "viewCount": 2374,
      "likeCount": 82,
      "commentCount": 9,
      "tags": [
        "문재인 펜스",
        "펜스 부통령",
        "미국 펜스",
        "문재인 펜스 접견",
        "평창동계올림픽",
        "평창올림픽",
        "평창",
        "비핵화"
      ],
      "categoryId": "25",
      "defaultLanguage": "ko",
      "defaultAudioLanguage": "ko",
      "liveBroadcastContent": "none",
      "liveStreamingDetails": {
        "actualStartTime": "2018-02-08T12:33:59Z",
        "actualEndTime": "2018-02-08T12:44:30Z"
      },
      "channelId": "UCIMOytYIzaUpoAM2bpT4JZQ",
      "channelName": "KTV 국민방송",
      "collectedAt": "2025-08-20T11:40:00.429175Z"
    },
    "t5OJa8NI9cA": {
      "videoId": "t5OJa8NI9cA",
      "title": "문재인 대통령, 한정 中 상무위원 접견결과 및 김영남, 김여정  방남 일정 청와대 브리핑",
      "description": "🎥[Live] 문재인 대통령, 한정 中 상무위원 접견 결과 및 김영남, 김여정 방남 일정 청와대 브리핑\n\n✔️#문재인 대통령은 10일 #김정은 북한 노동당 위원장의 여동생인 #김여정 노동당 중앙위원회 제1부부장을 포함한 북한 고위급 대표단을 접견하고 오찬을 함께 할 예정입니다.\n\n✔️북한 대표단은 9일 평창 동계올림픽 개막식에도 참석합니다.\n\n✔️이날 오찬 회동에서 김여정은 문 대통령에게 김정은 위원장의 친서를 전달할 가능성이 제기되고 있습니다.",
      "publishedAt": "2018-02-08T08:08:08Z",
      "duration": "PT4M16S",
      "viewCount": 2062,
      "likeCount": 113,
      "commentCount": 5,
      "tags": [
        "김영남",
        "김여정",
        "김영남 방남",
        "문재인",
        "남북관계",
        "평창올림픽",
        "평창동계올림픽",
        "문재인 대통령"
      ],
      "categoryId": "25",
      "defaultLanguage": null,
      "defaultAudioLanguage": null,
      "liveBroadcastContent": "none",
      "liveStreamingDetails": {
        "actualStartTime": "2018-02-08T07:20:14Z",
        "actualEndTime": "2018-02-08T07:35:25Z"
      },
      "channelId": "UCIMOytYIzaUpoAM2bpT4JZQ",
      "channelName": "KTV 국민방송",
      "collectedAt": "2025-08-20T11:40:00.429175Z"
    },
    "5l7EFRUP11g": {
      "videoId": "5l7EFRUP11g",
      "title": "[국민리포트] 평창 동계올림픽 D-1, 강원도 성화 봉송",
      "description": "세계인의 스포츠 축제인                  \n평창 동계올림픽이\n드디어 내일 화려한 막을 올립니다.\n\n지난 해 11월부터\n7천 5백명의 주자와 함께  \n대한민국 곳곳을 달려온\n올림픽 성화가\n평창 스타디움을\n밝히게 되는데요.  \n\n강원도를 누빈\n막바지 성화봉송 현장을\n다녀왔습니다.",
      "publishedAt": "2018-02-08T05:20:25Z",
      "duration": "PT2M51S",
      "viewCount": 581,
      "likeCount": 21,
      "commentCount": 1,
      "tags": [
        "KTV국민방송",
        "KTV정책방송",
        "국민방송KTV",
        "국민리포트",
        "국민SNS",
        "국민마이크",
        "국민인터뷰",
        "클래식영상미학",
        "정책SNS",
        "영상뉴스"
      ],
      "categoryId": "25",
      "defaultLanguage": null,
      "defaultAudioLanguage": "ko",
      "liveBroadcastContent": "none",
      "liveStreamingDetails": null,
      "channelId": "UCIMOytYIzaUpoAM2bpT4JZQ",
      "channelName": "KTV 국민방송",
      "collectedAt": "2025-08-20T11:40:00.429175Z"
    },
    "ZYQJqLB1ebk": {
      "videoId": "ZYQJqLB1ebk",
      "title": "[국민리포트] 탄자니아 대사관 개소…더 가까운 친구 나라로",
      "description": "아프리카 동남부의 탄자니아.\n우리나라와는\n1992년에 국교가 수립됐지만\n공식 대사관은\n없었던 상황인데요,\n\n주한 탄자니아 대사관이\n수교 26년 만에 \n문을 열어\n두 나라 관계에\n새로운 시작을 알렸습니다.\n\n그 현장에 다녀왔습니다.",
      "publishedAt": "2018-02-08T04:55:57Z",
      "duration": "PT3M35S",
      "viewCount": 2100,
      "likeCount": 32,
      "commentCount": 2,
      "tags": [
        "KTV국민방송",
        "KTV정책방송",
        "국민방송KTV",
        "국민리포트",
        "국민SNS",
        "국민마이크",
        "국민인터뷰",
        "클래식영상미학",
        "정책SNS",
        "영상뉴스"
      ],
      "categoryId": "25",
      "defaultLanguage": null,
      "defaultAudioLanguage": "ko",
      "liveBroadcastContent": "none",
      "liveStreamingDetails": null,
      "channelId": "UCIMOytYIzaUpoAM2bpT4JZQ",
      "channelName": "KTV 국민방송",
      "collectedAt": "2025-08-20T11:40:00.429175Z"
    },
    "4b2uVsYFsDQ": {
      "videoId": "4b2uVsYFsDQ",
      "title": "[국민리포트] 평창 동계올림픽…서울에서도 즐겨요",
      "description": "세계인의 스포츠 축제인\n평창 동계올림픽\n개막이 하루 앞으로\n다가왔는데요. \n\n올림픽 분위기를\n그대로 느낄 수 있는      \n다양한 볼거리와\n즐길거리가 \n서울시내 곳곳에서\n펼쳐지고 있습니다.",
      "publishedAt": "2018-02-08T04:55:39Z",
      "duration": "PT3M15S",
      "viewCount": 137,
      "likeCount": 5,
      "commentCount": 0,
      "tags": [
        "KTV국민방송",
        "KTV정책방송",
        "국민방송KTV",
        "국민리포트",
        "국민SNS",
        "국민마이크",
        "국민인터뷰",
        "클래식영상미학",
        "정책SNS",
        "영상뉴스"
      ],
      "categoryId": "25",
      "defaultLanguage": null,
      "defaultAudioLanguage": "ko",
      "liveBroadcastContent": "none",
      "liveStreamingDetails": null,
      "channelId": "UCIMOytYIzaUpoAM2bpT4JZQ",
      "channelName": "KTV 국민방송",
      "collectedAt": "2025-08-20T11:40:00.429175Z"
    },
    "D2a-qhm6loQ": {
      "videoId": "D2a-qhm6loQ",
      "title": "[국민리포트] 팔당호 한눈에…전망대 새 단장",
      "description": "팔당호를 한눈에 볼수있는 전망대가\n새롭게 단장해 문을 열었습니다.\n\n전망대와 함께 \n호수 생태계를 보여주는 \n환경 전시관도 문을 열었는데요. \n\n생태환경 체험 교육장으로도 \n한몫을 할것으로 기대됩니다.",
      "publishedAt": "2018-02-08T04:55:18Z",
      "duration": "PT2M43S",
      "viewCount": 252,
      "likeCount": 4,
      "commentCount": 0,
      "tags": [
        "KTV국민방송",
        "KTV정책방송",
        "국민방송KTV",
        "국민리포트",
        "국민SNS",
        "국민마이크",
        "국민인터뷰",
        "클래식영상미학",
        "정책SNS",
        "영상뉴스"
      ],
      "categoryId": "25",
      "defaultLanguage": null,
      "defaultAudioLanguage": "ko",
      "liveBroadcastContent": "none",
      "liveStreamingDetails": null,
      "channelId": "UCIMOytYIzaUpoAM2bpT4JZQ",
      "channelName": "KTV 국민방송",
      "collectedAt": "2025-08-20T11:40:00.429175Z"
    },
    "vkN8J6KQAxs": {
      "videoId": "vkN8J6KQAxs",
      "title": "MONOCLE + Bluehouse",
      "description": "MONOCLE + Bluehouse \n영국의 글로벌 라이프스타일 잡지 모노클MONOCLE 을 아세요? 모노클은 디지털이 주도하는 요즘의 언론환경 속에서도 소장가치 있는 콘텐츠를 만들어내며 주목을 받고 있는 잡지입니다. 모노클 3월호에 총 60여 페이지에 걸쳐 게재되는 한국 특집에 문재인 대통령과 김정숙 여사의 인터뷰도 실립니다. 모노클을 만난 문재인 대통령이 어떤 이야기를 나눴는지, 기대하세요.",
      "publishedAt": "2018-02-08T01:21:26Z",
      "duration": "PT58S",
      "viewCount": 52607,
      "likeCount": 2222,
      "commentCount": 295,
      "tags": [
        "모노클",
        "문재인",
        "청와대",
        "한국"
      ],
      "categoryId": "25",
      "defaultLanguage": null,
      "defaultAudioLanguage": null,
      "liveBroadcastContent": "none",
      "liveStreamingDetails": null,
      "channelId": "UC7WMB_czX5jF__5kqT4d9Ww",
      "channelName": " 문재인정부 청와대",
      "collectedAt": "2025-08-20T11:40:00.430172Z"
    },
    "6GXDWv-4VLY": {
      "videoId": "6GXDWv-4VLY",
      "title": "2월 8일 '11:50 청와대입니다'",
      "description": "1. 오늘의 대통령-5건의 정상외교 일정!  02:05\n2.평창 G-1 컬링경기와 북한예술단 공연 소식  04:47\n3.평화올림픽의 성공을 바라는 해외정상들의 메시지+대통령의 온라인 메시지  07:37\n4.문재인 대통령의 모노클 3월호 한국특집판 인터뷰 소개 13:30\n\n▶ 공식 홈페이지 http://www.president.go.kr\n▶ 공식 페이스북 https://www.facebook.com/TheBlueHouseKR\n▶ 공식 트위터 https://twitter.com/TheBlueHouseKR\n▶ 공식 인스타그램 https://www.instagram.com/thebluehouse_kr\n▶ 공식 네이버블로그 https://blog.naver.com/thebluehousekr",
      "publishedAt": "2018-02-08T03:46:09Z",
      "duration": "PT22M56S",
      "viewCount": 7839,
      "likeCount": 769,
      "commentCount": 39,
      "tags": [
        "청와대",
        "청와대페이스북라이브",
        "페이스북라이브",
        "고민정",
        "고민정부대변인",
        "고민정청와대",
        "청와대라이브",
        "11시50분청와대입니다",
        "11시50분청와대",
        "문재인"
      ],
      "categoryId": "25",
      "defaultLanguage": null,
      "defaultAudioLanguage": null,
      "liveBroadcastContent": "none",
      "liveStreamingDetails": {
        "actualStartTime": "2018-02-08T02:48:09Z",
        "actualEndTime": "2018-02-08T03:12:26Z"
      },
      "channelId": "UC7WMB_czX5jF__5kqT4d9Ww",
      "channelName": " 문재인정부 청와대",
      "collectedAt": "2025-08-20T11:40:00.430172Z"
    }
  },
  "channels": {
    "UCL-WOj1FxKR8Hlzg5tvnWKg": {
      "channelId": "UCL-WOj1FxKR8Hlzg5tvnWKg",
      "channelName": "NATV 국회방송",
      "channelUrl": "@natv_korea",
      "channelDescription": "대한민국 국회가 운영하는 '국회방송(NATV)'의 공식 유튜브 채널입니다.\n",
      "channelThumbnails": {
        "default": {
          "url": "https://yt3.ggpht.com/pR9h1UtIbvQgb1jzvA3cInTCuI9M_2tFxITGQb2pm7vlYy1lvoYmPMNrBQv7Rxhjy2Gh4FWGiQ=s88-c-k-c0x00ffffff-no-rj",
          "width": 88,
          "height": 88
        },
        "medium": {
          "url": "https://yt3.ggpht.com/pR9h1UtIbvQgb1jzvA3cInTCuI9M_2tFxITGQb2pm7vlYy1lvoYmPMNrBQv7Rxhjy2Gh4FWGiQ=s240-c-k-c0x00ffffff-no-rj",
          "width": 240,
          "height": 240
        },
        "high": {
          "url": "https://yt3.ggpht.com/pR9h1UtIbvQgb1jzvA3cInTCuI9M_2tFxITGQb2pm7vlYy1lvoYmPMNrBQv7Rxhjy2Gh4FWGiQ=s800-c-k-c0x00ffffff-no-rj",
          "width": 800,
          "height": 800
        }
      },
      "subscriberCount": 264000,
      "viewCount": 86009826,
      "videoCount": 16390,
      "lastUpdated": "2025-08-18T07:13:35.655982Z"
    },
    "UCIMOytYIzaUpoAM2bpT4JZQ": {
      "channelId": "UCIMOytYIzaUpoAM2bpT4JZQ",
      "channelName": "KTV 국민방송",
      "channelUrl": "@ktv_korea",
      "channelDescription": "이재명 정부 국정소식, 정책정보, 정부브리핑 등을 실시간으로 소개해드립니다\n",
      "channelThumbnails": {
        "default": {
          "url": "https://yt3.ggpht.com/C8SZ5Na4t2ExtMRDMXKbHJtoiC_2u30a4TjVoHpg4xLH0z2jUVntFrpGt26OXfkBHxuwjq8xTOk=s88-c-k-c0x00ffffff-no-rj",
          "width": 88,
          "height": 88
        },
        "medium": {
          "url": "https://yt3.ggpht.com/C8SZ5Na4t2ExtMRDMXKbHJtoiC_2u30a4TjVoHpg4xLH0z2jUVntFrpGt26OXfkBHxuwjq8xTOk=s240-c-k-c0x00ffffff-no-rj",
          "width": 240,
          "height": 240
        },
        "high": {
          "url": "https://yt3.ggpht.com/C8SZ5Na4t2ExtMRDMXKbHJtoiC_2u30a4TjVoHpg4xLH0z2jUVntFrpGt26OXfkBHxuwjq8xTOk=s800-c-k-c0x00ffffff-no-rj",
          "width": 800,
          "height": 800
        }
      },
      "subscriberCount": 594000,
      "viewCount": 496166667,
      "videoCount": 25206,
      "lastUpdated": "2025-08-20T11:40:00.429175Z"
    },
    "UC7WMB_czX5jF__5kqT4d9Ww": {
      "channelId": "UC7WMB_czX5jF__5kqT4d9Ww",
      "channelName": " 문재인정부 청와대",
      "channelUrl": "@thebluehousekr",
      "channelDescription": " 문재인정부 청와대 공식 유튜브 채널입니다.",
      "channelThumbnails": {
        "default": {
          "url": "https://yt3.ggpht.com/z0uFyY8invEc-QlNJod5ycMfMCwQiQlDNT4LWIyJqi4IL-XQc0F7OyYeBbJMhhaYJOs-ecL7VTo=s88-c-k-c0x00ffffff-no-rj",
          "width": 88,
          "height": 88
        },
        "medium": {
          "url": "https://yt3.ggpht.com/z0uFyY8invEc-QlNJod5ycMfMCwQiQlDNT4LWIyJqi4IL-XQc0F7OyYeBbJMhhaYJOs-ecL7VTo=s240-c-k-c0x00ffffff-no-rj",
          "width": 240,
          "height": 240
        },
        "high": {
          "url": "https://yt3.ggpht.com/z0uFyY8invEc-QlNJod5ycMfMCwQiQlDNT4LWIyJqi4IL-XQc0F7OyYeBbJMhhaYJOs-ecL7VTo=s800-c-k-c0x00ffffff-no-rj",
          "width": 800,
          "height": 800
        }
      },
      "subscriberCount": 308000,
      "viewCount": 58715833,
      "videoCount": 1549,
      "lastUpdated": "2025-08-20T11:40:00.429175Z"
    }
  },
  "lastUpdated": "2025-08-20T11:40:00.430172Z",
  "totalVideos": 13,
  "totalChannels": 3
}